Compiled from "GameRenderer.java"
public class net.minecraft.client.renderer.GameRenderer implements java.lang.AutoCloseable,net.minecraft.world.waypoints.TrackedWaypoint$Projector {
  private static final net.minecraft.resources.Identifier BLUR_POST_CHAIN_ID;

  public static final int MAX_BLUR_RADIUS;

  private static final org.slf4j.Logger LOGGER;

  public static final float PROJECTION_3D_HUD_Z_FAR;

  private static final float PORTAL_SPINNING_SPEED;

  private static final float NAUSEA_SPINNING_SPEED;

  private final net.minecraft.client.Minecraft minecraft;

  private final net.minecraft.client.renderer.state.GameRenderState gameRenderState;

  private final net.minecraft.util.RandomSource random;

  public final net.minecraft.client.renderer.ItemInHandRenderer itemInHandRenderer;

  private final net.minecraft.client.renderer.ScreenEffectRenderer screenEffectRenderer;

  private final net.minecraft.client.renderer.RenderBuffers renderBuffers;

  private float spinningEffectTime;

  private float spinningEffectSpeed;

  private float bossOverlayWorldDarkening;

  private float bossOverlayWorldDarkeningO;

  private boolean renderBlockOutline;

  private long lastScreenshotAttempt;

  private boolean hasWorldScreenshot;

  private final net.minecraft.client.renderer.Lightmap lightmap;

  private final net.minecraft.client.renderer.LightmapRenderStateExtractor lightmapRenderStateExtractor;

  private final net.minecraft.client.renderer.UiLightmap uiLightmap;

  private boolean useUiLightmap;

  private final net.minecraft.client.renderer.texture.OverlayTexture overlayTexture;

  protected final net.minecraft.client.renderer.Panorama panorama;

  private final com.mojang.blaze3d.resource.CrossFrameResourcePool resourcePool;

  private final net.minecraft.client.renderer.fog.FogRenderer fogRenderer;

  private final net.minecraft.client.gui.render.GuiRenderer guiRenderer;

  private final net.minecraft.client.renderer.SubmitNodeStorage submitNodeStorage;

  private final net.minecraft.client.renderer.feature.FeatureRenderDispatcher featureRenderDispatcher;

  private net.minecraft.resources.Identifier postEffectId;

  private boolean effectActive;

  private final net.minecraft.client.Camera mainCamera;

  private final net.minecraft.client.renderer.Projection hudProjection;

  private final com.mojang.blaze3d.platform.Lighting lighting;

  private final net.minecraft.client.renderer.GlobalSettingsUniform globalSettingsUniform;

  private final net.minecraft.client.renderer.ProjectionMatrixBuffer levelProjectionMatrixBuffer;

  private final net.minecraft.client.renderer.ProjectionMatrixBuffer hud3dProjectionMatrixBuffer;

  public net.minecraft.client.renderer.GameRenderer(net.minecraft.client.Minecraft, net.minecraft.client.renderer.ItemInHandRenderer, net.minecraft.client.renderer.RenderBuffers, net.minecraft.client.resources.model.ModelManager);
    Code:
       0: aload_0
       1: invokespecial #1                  // Method java/lang/Object."<init>":()V
       4: aload_0
       5: new           #7                  // class net/minecraft/client/renderer/state/GameRenderState
       8: dup
       9: invokespecial #9                  // Method net/minecraft/client/renderer/state/GameRenderState."<init>":()V
      12: putfield      #10                 // Field gameRenderState:Lnet/minecraft/client/renderer/state/GameRenderState;
      15: aload_0
      16: invokestatic  #16                 // InterfaceMethod net/minecraft/util/RandomSource.create:()Lnet/minecraft/util/RandomSource;
      19: putfield      #22                 // Field random:Lnet/minecraft/util/RandomSource;
      22: aload_0
      23: iconst_1
      24: putfield      #26                 // Field renderBlockOutline:Z
      27: aload_0
      28: new           #30                 // class net/minecraft/client/renderer/Lightmap
      31: dup
      32: invokespecial #32                 // Method net/minecraft/client/renderer/Lightmap."<init>":()V
      35: putfield      #33                 // Field lightmap:Lnet/minecraft/client/renderer/Lightmap;
      38: aload_0
      39: new           #37                 // class net/minecraft/client/renderer/UiLightmap
      42: dup
      43: invokespecial #39                 // Method net/minecraft/client/renderer/UiLightmap."<init>":()V
      46: putfield      #40                 // Field uiLightmap:Lnet/minecraft/client/renderer/UiLightmap;
      49: aload_0
      50: new           #44                 // class net/minecraft/client/renderer/texture/OverlayTexture
      53: dup
      54: invokespecial #46                 // Method net/minecraft/client/renderer/texture/OverlayTexture."<init>":()V
      57: putfield      #47                 // Field overlayTexture:Lnet/minecraft/client/renderer/texture/OverlayTexture;
      60: aload_0
      61: new           #51                 // class net/minecraft/client/renderer/Panorama
      64: dup
      65: invokespecial #53                 // Method net/minecraft/client/renderer/Panorama."<init>":()V
      68: putfield      #54                 // Field panorama:Lnet/minecraft/client/renderer/Panorama;
      71: aload_0
      72: new           #58                 // class com/mojang/blaze3d/resource/CrossFrameResourcePool
      75: dup
      76: iconst_3
      77: invokespecial #60                 // Method com/mojang/blaze3d/resource/CrossFrameResourcePool."<init>":(I)V
      80: putfield      #63                 // Field resourcePool:Lcom/mojang/blaze3d/resource/CrossFrameResourcePool;
      83: aload_0
      84: new           #67                 // class net/minecraft/client/renderer/fog/FogRenderer
      87: dup
      88: invokespecial #69                 // Method net/minecraft/client/renderer/fog/FogRenderer."<init>":()V
      91: putfield      #70                 // Field fogRenderer:Lnet/minecraft/client/renderer/fog/FogRenderer;
      94: aload_0
      95: new           #74                 // class net/minecraft/client/Camera
      98: dup
      99: invokespecial #76                 // Method net/minecraft/client/Camera."<init>":()V
     102: putfield      #77                 // Field mainCamera:Lnet/minecraft/client/Camera;
     105: aload_0
     106: new           #81                 // class net/minecraft/client/renderer/Projection
     109: dup
     110: invokespecial #83                 // Method net/minecraft/client/renderer/Projection."<init>":()V
     113: putfield      #84                 // Field hudProjection:Lnet/minecraft/client/renderer/Projection;
     116: aload_0
     117: new           #88                 // class com/mojang/blaze3d/platform/Lighting
     120: dup
     121: invokespecial #90                 // Method com/mojang/blaze3d/platform/Lighting."<init>":()V
     124: putfield      #91                 // Field lighting:Lcom/mojang/blaze3d/platform/Lighting;
     127: aload_0
     128: new           #95                 // class net/minecraft/client/renderer/GlobalSettingsUniform
     131: dup
     132: invokespecial #97                 // Method net/minecraft/client/renderer/GlobalSettingsUniform."<init>":()V
     135: putfield      #98                 // Field globalSettingsUniform:Lnet/minecraft/client/renderer/GlobalSettingsUniform;
     138: aload_0
     139: new           #102                // class net/minecraft/client/renderer/ProjectionMatrixBuffer
     142: dup
     143: ldc           #104                // String level
     145: invokespecial #106                // Method net/minecraft/client/renderer/ProjectionMatrixBuffer."<init>":(Ljava/lang/String;)V
     148: putfield      #109                // Field levelProjectionMatrixBuffer:Lnet/minecraft/client/renderer/ProjectionMatrixBuffer;
     151: aload_0
     152: new           #102                // class net/minecraft/client/renderer/ProjectionMatrixBuffer
     155: dup
     156: ldc           #113                // String 3d hud
     158: invokespecial #106                // Method net/minecraft/client/renderer/ProjectionMatrixBuffer."<init>":(Ljava/lang/String;)V
     161: putfield      #115                // Field hud3dProjectionMatrixBuffer:Lnet/minecraft/client/renderer/ProjectionMatrixBuffer;
     164: aload_0
     165: aload_1
     166: putfield      #118                // Field minecraft:Lnet/minecraft/client/Minecraft;
     169: aload_0
     170: aload_2
     171: putfield      #122                // Field itemInHandRenderer:Lnet/minecraft/client/renderer/ItemInHandRenderer;
     174: aload_0
     175: new           #126                // class net/minecraft/client/renderer/LightmapRenderStateExtractor
     178: dup
     179: aload_0
     180: aload_1
     181: invokespecial #128                // Method net/minecraft/client/renderer/LightmapRenderStateExtractor."<init>":(Lnet/minecraft/client/renderer/GameRenderer;Lnet/minecraft/client/Minecraft;)V
     184: putfield      #131                // Field lightmapRenderStateExtractor:Lnet/minecraft/client/renderer/LightmapRenderStateExtractor;
     187: aload_0
     188: aload_3
     189: putfield      #135                // Field renderBuffers:Lnet/minecraft/client/renderer/RenderBuffers;
     192: aload_3
     193: invokevirtual #139                // Method net/minecraft/client/renderer/RenderBuffers.bufferSource:()Lnet/minecraft/client/renderer/MultiBufferSource$BufferSource;
     196: astore        5
     198: aload_1
     199: invokevirtual #145                // Method net/minecraft/client/Minecraft.getAtlasManager:()Lnet/minecraft/client/resources/model/sprite/AtlasManager;
     202: astore        6
     204: aload_0
     205: new           #151                // class net/minecraft/client/renderer/SubmitNodeStorage
     208: dup
     209: invokespecial #153                // Method net/minecraft/client/renderer/SubmitNodeStorage."<init>":()V
     212: putfield      #154                // Field submitNodeStorage:Lnet/minecraft/client/renderer/SubmitNodeStorage;
     215: aload_0
     216: new           #158                // class net/minecraft/client/renderer/feature/FeatureRenderDispatcher
     219: dup
     220: aload_0
     221: getfield      #154                // Field submitNodeStorage:Lnet/minecraft/client/renderer/SubmitNodeStorage;
     224: aload         4
     226: aload         5
     228: aload         6
     230: aload_3
     231: invokevirtual #160                // Method net/minecraft/client/renderer/RenderBuffers.outlineBufferSource:()Lnet/minecraft/client/renderer/OutlineBufferSource;
     234: aload_3
     235: invokevirtual #164                // Method net/minecraft/client/renderer/RenderBuffers.crumblingBufferSource:()Lnet/minecraft/client/renderer/MultiBufferSource$BufferSource;
     238: aload_1
     239: getfield      #167                // Field net/minecraft/client/Minecraft.font:Lnet/minecraft/client/gui/Font;
     242: aload_0
     243: getfield      #10                 // Field gameRenderState:Lnet/minecraft/client/renderer/state/GameRenderState;
     246: invokespecial #171                // Method net/minecraft/client/renderer/feature/FeatureRenderDispatcher."<init>":(Lnet/minecraft/client/renderer/SubmitNodeStorage;Lnet/minecraft/client/resources/model/ModelManager;Lnet/minecraft/client/renderer/MultiBufferSource$BufferSource;Lnet/minecraft/client/resources/model/sprite/AtlasManager;Lnet/minecraft/client/renderer/OutlineBufferSource;Lnet/minecraft/client/renderer/MultiBufferSource$BufferSource;Lnet/minecraft/client/gui/Font;Lnet/minecraft/client/renderer/state/GameRenderState;)V
     249: putfield      #174                // Field featureRenderDispatcher:Lnet/minecraft/client/renderer/feature/FeatureRenderDispatcher;
     252: aload_0
     253: new           #178                // class net/minecraft/client/gui/render/GuiRenderer
     256: dup
     257: aload_0
     258: getfield      #10                 // Field gameRenderState:Lnet/minecraft/client/renderer/state/GameRenderState;
     261: getfield      #180                // Field net/minecraft/client/renderer/state/GameRenderState.guiRenderState:Lnet/minecraft/client/renderer/state/gui/GuiRenderState;
     264: aload         5
     266: aload_0
     267: getfield      #154                // Field submitNodeStorage:Lnet/minecraft/client/renderer/SubmitNodeStorage;
     270: aload_0
     271: getfield      #174                // Field featureRenderDispatcher:Lnet/minecraft/client/renderer/feature/FeatureRenderDispatcher;
     274: new           #184                // class net/minecraft/client/gui/render/pip/GuiEntityRenderer
     277: dup
     278: aload         5
     280: aload_1
     281: invokevirtual #186                // Method net/minecraft/client/Minecraft.getEntityRenderDispatcher:()Lnet/minecraft/client/renderer/entity/EntityRenderDispatcher;
     284: invokespecial #190                // Method net/minecraft/client/gui/render/pip/GuiEntityRenderer."<init>":(Lnet/minecraft/client/renderer/MultiBufferSource$BufferSource;Lnet/minecraft/client/renderer/entity/EntityRenderDispatcher;)V
     287: new           #193                // class net/minecraft/client/gui/render/pip/GuiSkinRenderer
     290: dup
     291: aload         5
     293: invokespecial #195                // Method net/minecraft/client/gui/render/pip/GuiSkinRenderer."<init>":(Lnet/minecraft/client/renderer/MultiBufferSource$BufferSource;)V
     296: new           #198                // class net/minecraft/client/gui/render/pip/GuiBookModelRenderer
     299: dup
     300: aload         5
     302: invokespecial #200                // Method net/minecraft/client/gui/render/pip/GuiBookModelRenderer."<init>":(Lnet/minecraft/client/renderer/MultiBufferSource$BufferSource;)V
     305: new           #201                // class net/minecraft/client/gui/render/pip/GuiBannerResultRenderer
     308: dup
     309: aload         5
     311: aload         6
     313: invokespecial #203                // Method net/minecraft/client/gui/render/pip/GuiBannerResultRenderer."<init>":(Lnet/minecraft/client/renderer/MultiBufferSource$BufferSource;Lnet/minecraft/client/resources/model/sprite/SpriteGetter;)V
     316: new           #206                // class net/minecraft/client/gui/render/pip/GuiSignRenderer
     319: dup
     320: aload         5
     322: aload         6
     324: invokespecial #208                // Method net/minecraft/client/gui/render/pip/GuiSignRenderer."<init>":(Lnet/minecraft/client/renderer/MultiBufferSource$BufferSource;Lnet/minecraft/client/resources/model/sprite/SpriteGetter;)V
     327: new           #209                // class net/minecraft/client/gui/render/pip/GuiProfilerChartRenderer
     330: dup
     331: aload         5
     333: invokespecial #211                // Method net/minecraft/client/gui/render/pip/GuiProfilerChartRenderer."<init>":(Lnet/minecraft/client/renderer/MultiBufferSource$BufferSource;)V
     336: invokestatic  #212                // InterfaceMethod java/util/List.of:(Ljava/lang/Object;Ljava/lang/Object;Ljava/lang/Object;Ljava/lang/Object;Ljava/lang/Object;Ljava/lang/Object;)Ljava/util/List;
     339: invokespecial #218                // Method net/minecraft/client/gui/render/GuiRenderer."<init>":(Lnet/minecraft/client/renderer/state/gui/GuiRenderState;Lnet/minecraft/client/renderer/MultiBufferSource$BufferSource;Lnet/minecraft/client/renderer/SubmitNodeCollector;Lnet/minecraft/client/renderer/feature/FeatureRenderDispatcher;Ljava/util/List;)V
     342: putfield      #221                // Field guiRenderer:Lnet/minecraft/client/gui/render/GuiRenderer;
     345: aload_0
     346: new           #225                // class net/minecraft/client/renderer/ScreenEffectRenderer
     349: dup
     350: aload_1
     351: aload         6
     353: aload         5
     355: invokespecial #227                // Method net/minecraft/client/renderer/ScreenEffectRenderer."<init>":(Lnet/minecraft/client/Minecraft;Lnet/minecraft/client/resources/model/sprite/SpriteGetter;Lnet/minecraft/client/renderer/MultiBufferSource;)V
     358: putfield      #230                // Field screenEffectRenderer:Lnet/minecraft/client/renderer/ScreenEffectRenderer;
     361: return

  public void close();
    Code:
       0: aload_0
       1: getfield      #98                 // Field globalSettingsUniform:Lnet/minecraft/client/renderer/GlobalSettingsUniform;
       4: invokevirtual #234                // Method net/minecraft/client/renderer/GlobalSettingsUniform.close:()V
       7: aload_0
       8: getfield      #33                 // Field lightmap:Lnet/minecraft/client/renderer/Lightmap;
      11: invokevirtual #237                // Method net/minecraft/client/renderer/Lightmap.close:()V
      14: aload_0
      15: getfield      #47                 // Field overlayTexture:Lnet/minecraft/client/renderer/texture/OverlayTexture;
      18: invokevirtual #238                // Method net/minecraft/client/renderer/texture/OverlayTexture.close:()V
      21: aload_0
      22: getfield      #40                 // Field uiLightmap:Lnet/minecraft/client/renderer/UiLightmap;
      25: invokevirtual #239                // Method net/minecraft/client/renderer/UiLightmap.close:()V
      28: aload_0
      29: getfield      #63                 // Field resourcePool:Lcom/mojang/blaze3d/resource/CrossFrameResourcePool;
      32: invokevirtual #240                // Method com/mojang/blaze3d/resource/CrossFrameResourcePool.close:()V
      35: aload_0
      36: getfield      #221                // Field guiRenderer:Lnet/minecraft/client/gui/render/GuiRenderer;
      39: invokevirtual #241                // Method net/minecraft/client/gui/render/GuiRenderer.close:()V
      42: aload_0
      43: getfield      #109                // Field levelProjectionMatrixBuffer:Lnet/minecraft/client/renderer/ProjectionMatrixBuffer;
      46: invokevirtual #242                // Method net/minecraft/client/renderer/ProjectionMatrixBuffer.close:()V
      49: aload_0
      50: getfield      #115                // Field hud3dProjectionMatrixBuffer:Lnet/minecraft/client/renderer/ProjectionMatrixBuffer;
      53: invokevirtual #242                // Method net/minecraft/client/renderer/ProjectionMatrixBuffer.close:()V
      56: aload_0
      57: getfield      #91                 // Field lighting:Lcom/mojang/blaze3d/platform/Lighting;
      60: invokevirtual #243                // Method com/mojang/blaze3d/platform/Lighting.close:()V
      63: aload_0
      64: getfield      #70                 // Field fogRenderer:Lnet/minecraft/client/renderer/fog/FogRenderer;
      67: invokevirtual #244                // Method net/minecraft/client/renderer/fog/FogRenderer.close:()V
      70: aload_0
      71: getfield      #174                // Field featureRenderDispatcher:Lnet/minecraft/client/renderer/feature/FeatureRenderDispatcher;
      74: invokevirtual #245                // Method net/minecraft/client/renderer/feature/FeatureRenderDispatcher.close:()V
      77: return

  public net.minecraft.client.renderer.SubmitNodeStorage getSubmitNodeStorage();
    Code:
       0: aload_0
       1: getfield      #154                // Field submitNodeStorage:Lnet/minecraft/client/renderer/SubmitNodeStorage;
       4: areturn

  public net.minecraft.client.renderer.feature.FeatureRenderDispatcher getFeatureRenderDispatcher();
    Code:
       0: aload_0
       1: getfield      #174                // Field featureRenderDispatcher:Lnet/minecraft/client/renderer/feature/FeatureRenderDispatcher;
       4: areturn

  public net.minecraft.client.renderer.state.GameRenderState getGameRenderState();
    Code:
       0: aload_0
       1: getfield      #10                 // Field gameRenderState:Lnet/minecraft/client/renderer/state/GameRenderState;
       4: areturn

  public void setRenderBlockOutline(boolean);
    Code:
       0: aload_0
       1: iload_1
       2: putfield      #26                 // Field renderBlockOutline:Z
       5: return

  public void clearPostEffect();
    Code:
       0: aload_0
       1: aconst_null
       2: putfield      #246                // Field postEffectId:Lnet/minecraft/resources/Identifier;
       5: aload_0
       6: iconst_0
       7: putfield      #250                // Field effectActive:Z
      10: return

  public void togglePostEffect();
    Code:
       0: aload_0
       1: aload_0
       2: getfield      #250                // Field effectActive:Z
       5: ifne          12
       8: iconst_1
       9: goto          13
      12: iconst_0
      13: putfield      #250                // Field effectActive:Z
      16: return

  public void checkEntityPostEffect(net.minecraft.world.entity.Entity);
    Code:
       0: aload_1
       1: astore_2
       2: iconst_0
       3: istore_3
       4: aload_2
       5: iload_3
       6: invokedynamic #253,  0            // InvokeDynamic #0:typeSwitch:(Lnet/minecraft/world/entity/Entity;I)I
      11: tableswitch   { // -1 to 2
                    -1: 97
                     0: 40
                     1: 59
                     2: 78
               default: 97
          }
      40: aload_2
      41: checkcast     #257                // class net/minecraft/world/entity/monster/Creeper
      44: astore        4
      46: aload_0
      47: ldc_w         #259                // String creeper
      50: invokestatic  #261                // Method net/minecraft/resources/Identifier.withDefaultNamespace:(Ljava/lang/String;)Lnet/minecraft/resources/Identifier;
      53: invokevirtual #267                // Method setPostEffect:(Lnet/minecraft/resources/Identifier;)V
      56: goto          101
      59: aload_2
      60: checkcast     #271                // class net/minecraft/world/entity/monster/spider/Spider
      63: astore        5
      65: aload_0
      66: ldc_w         #273                // String spider
      69: invokestatic  #261                // Method net/minecraft/resources/Identifier.withDefaultNamespace:(Ljava/lang/String;)Lnet/minecraft/resources/Identifier;
      72: invokevirtual #267                // Method setPostEffect:(Lnet/minecraft/resources/Identifier;)V
      75: goto          101
      78: aload_2
      79: checkcast     #275                // class net/minecraft/world/entity/monster/EnderMan
      82: astore        6
      84: aload_0
      85: ldc_w         #277                // String invert
      88: invokestatic  #261                // Method net/minecraft/resources/Identifier.withDefaultNamespace:(Ljava/lang/String;)Lnet/minecraft/resources/Identifier;
      91: invokevirtual #267                // Method setPostEffect:(Lnet/minecraft/resources/Identifier;)V
      94: goto          101
      97: aload_0
      98: invokevirtual #279                // Method clearPostEffect:()V
     101: return

  private void setPostEffect(net.minecraft.resources.Identifier);
    Code:
       0: aload_0
       1: aload_1
       2: putfield      #246                // Field postEffectId:Lnet/minecraft/resources/Identifier;
       5: aload_0
       6: iconst_1
       7: putfield      #250                // Field effectActive:Z
      10: return

  public void processBlurEffect();
    Code:
       0: aload_0
       1: getfield      #118                // Field minecraft:Lnet/minecraft/client/Minecraft;
       4: invokevirtual #282                // Method net/minecraft/client/Minecraft.getShaderManager:()Lnet/minecraft/client/renderer/ShaderManager;
       7: getstatic     #286                // Field BLUR_POST_CHAIN_ID:Lnet/minecraft/resources/Identifier;
      10: getstatic     #289                // Field net/minecraft/client/renderer/LevelTargetBundle.MAIN_TARGETS:Ljava/util/Set;
      13: invokevirtual #295                // Method net/minecraft/client/renderer/ShaderManager.getPostChain:(Lnet/minecraft/resources/Identifier;Ljava/util/Set;)Lnet/minecraft/client/renderer/PostChain;
      16: astore_1
      17: aload_1
      18: ifnull        36
      21: aload_1
      22: aload_0
      23: getfield      #118                // Field minecraft:Lnet/minecraft/client/Minecraft;
      26: invokevirtual #301                // Method net/minecraft/client/Minecraft.getMainRenderTarget:()Lcom/mojang/blaze3d/pipeline/RenderTarget;
      29: aload_0
      30: getfield      #63                 // Field resourcePool:Lcom/mojang/blaze3d/resource/CrossFrameResourcePool;
      33: invokevirtual #305                // Method net/minecraft/client/renderer/PostChain.process:(Lcom/mojang/blaze3d/pipeline/RenderTarget;Lcom/mojang/blaze3d/resource/GraphicsResourceAllocator;)V
      36: return

  public void preloadUiShader(net.minecraft.server.packs.resources.ResourceProvider);
    Code:
       0: invokestatic  #311                // Method com/mojang/blaze3d/systems/RenderSystem.getDevice:()Lcom/mojang/blaze3d/systems/GpuDevice;
       3: astore_2
       4: aload_1
       5: invokedynamic #317,  0            // InvokeDynamic #1:get:(Lnet/minecraft/server/packs/resources/ResourceProvider;)Lcom/mojang/blaze3d/shaders/ShaderSource;
      10: astore_3
      11: aload_2
      12: getstatic     #321                // Field net/minecraft/client/renderer/RenderPipelines.GUI:Lcom/mojang/blaze3d/pipeline/RenderPipeline;
      15: aload_3
      16: invokevirtual #327                // Method com/mojang/blaze3d/systems/GpuDevice.precompilePipeline:(Lcom/mojang/blaze3d/pipeline/RenderPipeline;Lcom/mojang/blaze3d/shaders/ShaderSource;)Lcom/mojang/blaze3d/pipeline/CompiledRenderPipeline;
      19: pop
      20: aload_2
      21: getstatic     #333                // Field net/minecraft/client/renderer/RenderPipelines.GUI_TEXTURED:Lcom/mojang/blaze3d/pipeline/RenderPipeline;
      24: aload_3
      25: invokevirtual #327                // Method com/mojang/blaze3d/systems/GpuDevice.precompilePipeline:(Lcom/mojang/blaze3d/pipeline/RenderPipeline;Lcom/mojang/blaze3d/shaders/ShaderSource;)Lcom/mojang/blaze3d/pipeline/CompiledRenderPipeline;
      28: pop
      29: invokestatic  #336                // Method com/mojang/jtracy/TracyClient.isAvailable:()Z
      32: ifeq          44
      35: aload_2
      36: getstatic     #342                // Field net/minecraft/client/renderer/RenderPipelines.TRACY_BLIT:Lcom/mojang/blaze3d/pipeline/RenderPipeline;
      39: aload_3
      40: invokevirtual #327                // Method com/mojang/blaze3d/systems/GpuDevice.precompilePipeline:(Lcom/mojang/blaze3d/pipeline/RenderPipeline;Lcom/mojang/blaze3d/shaders/ShaderSource;)Lcom/mojang/blaze3d/pipeline/CompiledRenderPipeline;
      43: pop
      44: return

  public void tick();
    Code:
       0: aload_0
       1: getfield      #131                // Field lightmapRenderStateExtractor:Lnet/minecraft/client/renderer/LightmapRenderStateExtractor;
       4: invokevirtual #345                // Method net/minecraft/client/renderer/LightmapRenderStateExtractor.tick:()V
       7: aload_0
       8: getfield      #118                // Field minecraft:Lnet/minecraft/client/Minecraft;
      11: getfield      #348                // Field net/minecraft/client/Minecraft.player:Lnet/minecraft/client/player/LocalPlayer;
      14: astore_1
      15: aload_0
      16: getfield      #77                 // Field mainCamera:Lnet/minecraft/client/Camera;
      19: invokevirtual #352                // Method net/minecraft/client/Camera.entity:()Lnet/minecraft/world/entity/Entity;
      22: ifnonnull     33
      25: aload_0
      26: getfield      #77                 // Field mainCamera:Lnet/minecraft/client/Camera;
      29: aload_1
      30: invokevirtual #356                // Method net/minecraft/client/Camera.setEntity:(Lnet/minecraft/world/entity/Entity;)V
      33: aload_0
      34: getfield      #77                 // Field mainCamera:Lnet/minecraft/client/Camera;
      37: invokevirtual #360                // Method net/minecraft/client/Camera.tick:()V
      40: aload_0
      41: getfield      #122                // Field itemInHandRenderer:Lnet/minecraft/client/renderer/ItemInHandRenderer;
      44: invokevirtual #361                // Method net/minecraft/client/renderer/ItemInHandRenderer.tick:()V
      47: aload_1
      48: getfield      #364                // Field net/minecraft/client/player/LocalPlayer.portalEffectIntensity:F
      51: fstore_2
      52: aload_1
      53: getstatic     #370                // Field net/minecraft/world/effect/MobEffects.NAUSEA:Lnet/minecraft/core/Holder;
      56: fconst_1
      57: invokevirtual #376                // Method net/minecraft/client/player/LocalPlayer.getEffectBlendFactor:(Lnet/minecraft/core/Holder;F)F
      60: fstore_3
      61: fload_2
      62: fconst_0
      63: fcmpl
      64: ifgt          73
      67: fload_3
      68: fconst_0
      69: fcmpl
      70: ifle          108
      73: aload_0
      74: fload_2
      75: ldc_w         #380                // float 20.0f
      78: fmul
      79: fload_3
      80: ldc_w         #381                // float 7.0f
      83: fmul
      84: fadd
      85: fload_2
      86: fload_3
      87: fadd
      88: fdiv
      89: putfield      #382                // Field spinningEffectSpeed:F
      92: aload_0
      93: dup
      94: getfield      #385                // Field spinningEffectTime:F
      97: aload_0
      98: getfield      #382                // Field spinningEffectSpeed:F
     101: fadd
     102: putfield      #385                // Field spinningEffectTime:F
     105: goto          113
     108: aload_0
     109: fconst_0
     110: putfield      #382                // Field spinningEffectSpeed:F
     113: aload_0
     114: getfield      #118                // Field minecraft:Lnet/minecraft/client/Minecraft;
     117: getfield      #388                // Field net/minecraft/client/Minecraft.level:Lnet/minecraft/client/multiplayer/ClientLevel;
     120: invokevirtual #391                // Method net/minecraft/client/multiplayer/ClientLevel.tickRateManager:()Lnet/minecraft/world/TickRateManager;
     123: invokevirtual #397                // Method net/minecraft/world/TickRateManager.runsNormally:()Z
     126: ifne          130
     129: return
     130: aload_0
     131: aload_0
     132: getfield      #402                // Field bossOverlayWorldDarkening:F
     135: putfield      #405                // Field bossOverlayWorldDarkeningO:F
     138: aload_0
     139: getfield      #118                // Field minecraft:Lnet/minecraft/client/Minecraft;
     142: getfield      #408                // Field net/minecraft/client/Minecraft.gui:Lnet/minecraft/client/gui/Gui;
     145: invokevirtual #412                // Method net/minecraft/client/gui/Gui.getBossOverlay:()Lnet/minecraft/client/gui/components/BossHealthOverlay;
     148: invokevirtual #418                // Method net/minecraft/client/gui/components/BossHealthOverlay.shouldDarkenScreen:()Z
     151: ifeq          183
     154: aload_0
     155: dup
     156: getfield      #402                // Field bossOverlayWorldDarkening:F
     159: ldc_w         #425                // float 0.05f
     162: fadd
     163: putfield      #402                // Field bossOverlayWorldDarkening:F
     166: aload_0
     167: getfield      #402                // Field bossOverlayWorldDarkening:F
     170: fconst_1
     171: fcmpl
     172: ifle          204
     175: aload_0
     176: fconst_1
     177: putfield      #402                // Field bossOverlayWorldDarkening:F
     180: goto          204
     183: aload_0
     184: getfield      #402                // Field bossOverlayWorldDarkening:F
     187: fconst_0
     188: fcmpl
     189: ifle          204
     192: aload_0
     193: dup
     194: getfield      #402                // Field bossOverlayWorldDarkening:F
     197: ldc_w         #426                // float 0.0125f
     200: fsub
     201: putfield      #402                // Field bossOverlayWorldDarkening:F
     204: aload_0
     205: getfield      #230                // Field screenEffectRenderer:Lnet/minecraft/client/renderer/ScreenEffectRenderer;
     208: invokevirtual #427                // Method net/minecraft/client/renderer/ScreenEffectRenderer.tick:()V
     211: invokestatic  #428                // Method net/minecraft/util/profiling/Profiler.get:()Lnet/minecraft/util/profiling/ProfilerFiller;
     214: astore        4
     216: aload         4
     218: ldc_w         #433                // String levelRenderer
     221: invokeinterface #435,  2          // InterfaceMethod net/minecraft/util/profiling/ProfilerFiller.push:(Ljava/lang/String;)V
     226: aload_0
     227: getfield      #118                // Field minecraft:Lnet/minecraft/client/Minecraft;
     230: getfield      #440                // Field net/minecraft/client/Minecraft.levelRenderer:Lnet/minecraft/client/renderer/LevelRenderer;
     233: aload_0
     234: getfield      #77                 // Field mainCamera:Lnet/minecraft/client/Camera;
     237: invokevirtual #443                // Method net/minecraft/client/renderer/LevelRenderer.tick:(Lnet/minecraft/client/Camera;)V
     240: aload         4
     242: invokeinterface #448,  1          // InterfaceMethod net/minecraft/util/profiling/ProfilerFiller.pop:()V
     247: return

  public net.minecraft.resources.Identifier currentPostEffect();
    Code:
       0: aload_0
       1: getfield      #246                // Field postEffectId:Lnet/minecraft/resources/Identifier;
       4: areturn

  public void resize(int, int);
    Code:
       0: aload_0
       1: getfield      #63                 // Field resourcePool:Lcom/mojang/blaze3d/resource/CrossFrameResourcePool;
       4: invokevirtual #451                // Method com/mojang/blaze3d/resource/CrossFrameResourcePool.clear:()V
       7: aload_0
       8: getfield      #118                // Field minecraft:Lnet/minecraft/client/Minecraft;
      11: invokevirtual #301                // Method net/minecraft/client/Minecraft.getMainRenderTarget:()Lcom/mojang/blaze3d/pipeline/RenderTarget;
      14: astore_3
      15: aload_3
      16: iload_1
      17: iload_2
      18: invokevirtual #454                // Method com/mojang/blaze3d/pipeline/RenderTarget.resize:(II)V
      21: aload_0
      22: getfield      #118                // Field minecraft:Lnet/minecraft/client/Minecraft;
      25: getfield      #440                // Field net/minecraft/client/Minecraft.levelRenderer:Lnet/minecraft/client/renderer/LevelRenderer;
      28: iload_1
      29: iload_2
      30: invokevirtual #460                // Method net/minecraft/client/renderer/LevelRenderer.resize:(II)V
      33: return

  private void bobHurt(net.minecraft.client.renderer.state.level.CameraRenderState, com.mojang.blaze3d.vertex.PoseStack);
    Code:
       0: aload_1
       1: getfield      #461                // Field net/minecraft/client/renderer/state/level/CameraRenderState.entityRenderState:Lnet/minecraft/client/renderer/state/level/CameraEntityRenderState;
       4: getfield      #467                // Field net/minecraft/client/renderer/state/level/CameraEntityRenderState.isLiving:Z
       7: ifeq          176
      10: aload_1
      11: getfield      #461                // Field net/minecraft/client/renderer/state/level/CameraRenderState.entityRenderState:Lnet/minecraft/client/renderer/state/level/CameraEntityRenderState;
      14: getfield      #472                // Field net/minecraft/client/renderer/state/level/CameraEntityRenderState.hurtTime:F
      17: fstore_3
      18: aload_1
      19: getfield      #461                // Field net/minecraft/client/renderer/state/level/CameraRenderState.entityRenderState:Lnet/minecraft/client/renderer/state/level/CameraEntityRenderState;
      22: getfield      #475                // Field net/minecraft/client/renderer/state/level/CameraEntityRenderState.isDeadOrDying:Z
      25: ifeq          69
      28: aload_1
      29: getfield      #461                // Field net/minecraft/client/renderer/state/level/CameraRenderState.entityRenderState:Lnet/minecraft/client/renderer/state/level/CameraEntityRenderState;
      32: getfield      #478                // Field net/minecraft/client/renderer/state/level/CameraEntityRenderState.deathTime:F
      35: ldc_w         #380                // float 20.0f
      38: invokestatic  #483                // Method java/lang/Math.min:(FF)F
      41: fstore        4
      43: aload_2
      44: getstatic     #489                // Field com/mojang/math/Axis.ZP:Lcom/mojang/math/Axis;
      47: ldc_w         #495                // float 40.0f
      50: ldc_w         #496                // float 8000.0f
      53: fload         4
      55: ldc_w         #497                // float 200.0f
      58: fadd
      59: fdiv
      60: fsub
      61: invokeinterface #498,  2          // InterfaceMethod com/mojang/math/Axis.rotationDegrees:(F)Lorg/joml/Quaternionf;
      66: invokevirtual #502                // Method com/mojang/blaze3d/vertex/PoseStack.mulPose:(Lorg/joml/Quaternionfc;)V
      69: fload_3
      70: fconst_0
      71: fcmpg
      72: ifge          76
      75: return
      76: fload_3
      77: aload_1
      78: getfield      #461                // Field net/minecraft/client/renderer/state/level/CameraRenderState.entityRenderState:Lnet/minecraft/client/renderer/state/level/CameraEntityRenderState;
      81: getfield      #508                // Field net/minecraft/client/renderer/state/level/CameraEntityRenderState.hurtDuration:I
      84: i2f
      85: fdiv
      86: fstore_3
      87: fload_3
      88: fload_3
      89: fmul
      90: fload_3
      91: fmul
      92: fload_3
      93: fmul
      94: ldc_w         #514                // float 3.1415927f
      97: fmul
      98: f2d
      99: invokestatic  #515                // Method net/minecraft/util/Mth.sin:(D)F
     102: fstore_3
     103: aload_1
     104: getfield      #461                // Field net/minecraft/client/renderer/state/level/CameraRenderState.entityRenderState:Lnet/minecraft/client/renderer/state/level/CameraEntityRenderState;
     107: getfield      #519                // Field net/minecraft/client/renderer/state/level/CameraEntityRenderState.hurtDir:F
     110: fstore        4
     112: aload_2
     113: getstatic     #522                // Field com/mojang/math/Axis.YP:Lcom/mojang/math/Axis;
     116: fload         4
     118: fneg
     119: invokeinterface #498,  2          // InterfaceMethod com/mojang/math/Axis.rotationDegrees:(F)Lorg/joml/Quaternionf;
     124: invokevirtual #502                // Method com/mojang/blaze3d/vertex/PoseStack.mulPose:(Lorg/joml/Quaternionfc;)V
     127: fload_3
     128: fneg
     129: f2d
     130: ldc2_w        #525                // double 14.0d
     133: dmul
     134: aload_0
     135: getfield      #10                 // Field gameRenderState:Lnet/minecraft/client/renderer/state/GameRenderState;
     138: getfield      #527                // Field net/minecraft/client/renderer/state/GameRenderState.optionsRenderState:Lnet/minecraft/client/renderer/state/OptionsRenderState;
     141: getfield      #531                // Field net/minecraft/client/renderer/state/OptionsRenderState.damageTiltStrength:D
     144: dmul
     145: d2f
     146: fstore        5
     148: aload_2
     149: getstatic     #489                // Field com/mojang/math/Axis.ZP:Lcom/mojang/math/Axis;
     152: fload         5
     154: invokeinterface #498,  2          // InterfaceMethod com/mojang/math/Axis.rotationDegrees:(F)Lorg/joml/Quaternionf;
     159: invokevirtual #502                // Method com/mojang/blaze3d/vertex/PoseStack.mulPose:(Lorg/joml/Quaternionfc;)V
     162: aload_2
     163: getstatic     #522                // Field com/mojang/math/Axis.YP:Lcom/mojang/math/Axis;
     166: fload         4
     168: invokeinterface #498,  2          // InterfaceMethod com/mojang/math/Axis.rotationDegrees:(F)Lorg/joml/Quaternionf;
     173: invokevirtual #502                // Method com/mojang/blaze3d/vertex/PoseStack.mulPose:(Lorg/joml/Quaternionfc;)V
     176: return

  private void bobView(net.minecraft.client.renderer.state.level.CameraRenderState, com.mojang.blaze3d.vertex.PoseStack);
    Code:
       0: aload_1
       1: getfield      #461                // Field net/minecraft/client/renderer/state/level/CameraRenderState.entityRenderState:Lnet/minecraft/client/renderer/state/level/CameraEntityRenderState;
       4: getfield      #537                // Field net/minecraft/client/renderer/state/level/CameraEntityRenderState.isPlayer:Z
       7: ifne          11
      10: return
      11: aload_1
      12: getfield      #461                // Field net/minecraft/client/renderer/state/level/CameraRenderState.entityRenderState:Lnet/minecraft/client/renderer/state/level/CameraEntityRenderState;
      15: getfield      #540                // Field net/minecraft/client/renderer/state/level/CameraEntityRenderState.backwardsInterpolatedWalkDistance:F
      18: fstore_3
      19: aload_1
      20: getfield      #461                // Field net/minecraft/client/renderer/state/level/CameraRenderState.entityRenderState:Lnet/minecraft/client/renderer/state/level/CameraEntityRenderState;
      23: getfield      #543                // Field net/minecraft/client/renderer/state/level/CameraEntityRenderState.bob:F
      26: fstore        4
      28: aload_2
      29: fload_3
      30: ldc_w         #514                // float 3.1415927f
      33: fmul
      34: f2d
      35: invokestatic  #515                // Method net/minecraft/util/Mth.sin:(D)F
      38: fload         4
      40: fmul
      41: ldc_w         #546                // float 0.5f
      44: fmul
      45: fload_3
      46: ldc_w         #514                // float 3.1415927f
      49: fmul
      50: f2d
      51: invokestatic  #547                // Method net/minecraft/util/Mth.cos:(D)F
      54: fload         4
      56: fmul
      57: invokestatic  #550                // Method java/lang/Math.abs:(F)F
      60: fneg
      61: fconst_0
      62: invokevirtual #554                // Method com/mojang/blaze3d/vertex/PoseStack.translate:(FFF)V
      65: aload_2
      66: getstatic     #489                // Field com/mojang/math/Axis.ZP:Lcom/mojang/math/Axis;
      69: fload_3
      70: ldc_w         #514                // float 3.1415927f
      73: fmul
      74: f2d
      75: invokestatic  #515                // Method net/minecraft/util/Mth.sin:(D)F
      78: fload         4
      80: fmul
      81: ldc_w         #558                // float 3.0f
      84: fmul
      85: invokeinterface #498,  2          // InterfaceMethod com/mojang/math/Axis.rotationDegrees:(F)Lorg/joml/Quaternionf;
      90: invokevirtual #502                // Method com/mojang/blaze3d/vertex/PoseStack.mulPose:(Lorg/joml/Quaternionfc;)V
      93: aload_2
      94: getstatic     #559                // Field com/mojang/math/Axis.XP:Lcom/mojang/math/Axis;
      97: fload_3
      98: ldc_w         #514                // float 3.1415927f
     101: fmul
     102: ldc_w         #562                // float 0.2f
     105: fsub
     106: f2d
     107: invokestatic  #547                // Method net/minecraft/util/Mth.cos:(D)F
     110: fload         4
     112: fmul
     113: invokestatic  #550                // Method java/lang/Math.abs:(F)F
     116: ldc_w         #563                // float 5.0f
     119: fmul
     120: invokeinterface #498,  2          // InterfaceMethod com/mojang/math/Axis.rotationDegrees:(F)Lorg/joml/Quaternionf;
     125: invokevirtual #502                // Method com/mojang/blaze3d/vertex/PoseStack.mulPose:(Lorg/joml/Quaternionfc;)V
     128: return

  private void renderItemInHand(net.minecraft.client.renderer.state.level.CameraRenderState, float, org.joml.Matrix4fc);
    Code:
       0: aload_1
       1: getfield      #564                // Field net/minecraft/client/renderer/state/level/CameraRenderState.isPanoramicMode:Z
       4: ifeq          8
       7: return
       8: aload_0
       9: getfield      #174                // Field featureRenderDispatcher:Lnet/minecraft/client/renderer/feature/FeatureRenderDispatcher;
      12: invokevirtual #567                // Method net/minecraft/client/renderer/feature/FeatureRenderDispatcher.renderAllFeatures:()V
      15: aload_0
      16: getfield      #135                // Field renderBuffers:Lnet/minecraft/client/renderer/RenderBuffers;
      19: invokevirtual #139                // Method net/minecraft/client/renderer/RenderBuffers.bufferSource:()Lnet/minecraft/client/renderer/MultiBufferSource$BufferSource;
      22: invokevirtual #570                // Method net/minecraft/client/renderer/MultiBufferSource$BufferSource.endBatch:()V
      25: new           #503                // class com/mojang/blaze3d/vertex/PoseStack
      28: dup
      29: invokespecial #575                // Method com/mojang/blaze3d/vertex/PoseStack."<init>":()V
      32: astore        4
      34: aload         4
      36: invokevirtual #576                // Method com/mojang/blaze3d/vertex/PoseStack.pushPose:()V
      39: aload         4
      41: aload_3
      42: new           #579                // class org/joml/Matrix4f
      45: dup
      46: invokespecial #581                // Method org/joml/Matrix4f."<init>":()V
      49: invokeinterface #582,  2          // InterfaceMethod org/joml/Matrix4fc.invert:(Lorg/joml/Matrix4f;)Lorg/joml/Matrix4f;
      54: invokevirtual #587                // Method com/mojang/blaze3d/vertex/PoseStack.mulPose:(Lorg/joml/Matrix4fc;)V
      57: invokestatic  #590                // Method com/mojang/blaze3d/systems/RenderSystem.getModelViewStack:()Lorg/joml/Matrix4fStack;
      60: astore        5
      62: aload         5
      64: invokevirtual #594                // Method org/joml/Matrix4fStack.pushMatrix:()Lorg/joml/Matrix4fStack;
      67: aload_3
      68: invokevirtual #599                // Method org/joml/Matrix4fStack.mul:(Lorg/joml/Matrix4fc;)Lorg/joml/Matrix4f;
      71: pop
      72: aload_0
      73: aload_1
      74: aload         4
      76: invokevirtual #603                // Method bobHurt:(Lnet/minecraft/client/renderer/state/level/CameraRenderState;Lcom/mojang/blaze3d/vertex/PoseStack;)V
      79: aload_0
      80: getfield      #10                 // Field gameRenderState:Lnet/minecraft/client/renderer/state/GameRenderState;
      83: getfield      #527                // Field net/minecraft/client/renderer/state/GameRenderState.optionsRenderState:Lnet/minecraft/client/renderer/state/OptionsRenderState;
      86: getfield      #607                // Field net/minecraft/client/renderer/state/OptionsRenderState.bobView:Z
      89: ifeq          99
      92: aload_0
      93: aload_1
      94: aload         4
      96: invokevirtual #610                // Method bobView:(Lnet/minecraft/client/renderer/state/level/CameraRenderState;Lcom/mojang/blaze3d/vertex/PoseStack;)V
      99: aload_0
     100: getfield      #10                 // Field gameRenderState:Lnet/minecraft/client/renderer/state/GameRenderState;
     103: getfield      #527                // Field net/minecraft/client/renderer/state/GameRenderState.optionsRenderState:Lnet/minecraft/client/renderer/state/OptionsRenderState;
     106: getfield      #612                // Field net/minecraft/client/renderer/state/OptionsRenderState.cameraType:Lnet/minecraft/client/CameraType;
     109: invokevirtual #616                // Method net/minecraft/client/CameraType.isFirstPerson:()Z
     112: ifeq          199
     115: aload_1
     116: getfield      #461                // Field net/minecraft/client/renderer/state/level/CameraRenderState.entityRenderState:Lnet/minecraft/client/renderer/state/level/CameraEntityRenderState;
     119: getfield      #621                // Field net/minecraft/client/renderer/state/level/CameraEntityRenderState.isSleeping:Z
     122: ifne          199
     125: aload_0
     126: getfield      #10                 // Field gameRenderState:Lnet/minecraft/client/renderer/state/GameRenderState;
     129: getfield      #527                // Field net/minecraft/client/renderer/state/GameRenderState.optionsRenderState:Lnet/minecraft/client/renderer/state/OptionsRenderState;
     132: getfield      #624                // Field net/minecraft/client/renderer/state/OptionsRenderState.hideGui:Z
     135: ifne          199
     138: aload_0
     139: getfield      #118                // Field minecraft:Lnet/minecraft/client/Minecraft;
     142: getfield      #627                // Field net/minecraft/client/Minecraft.gameMode:Lnet/minecraft/client/multiplayer/MultiPlayerGameMode;
     145: invokevirtual #631                // Method net/minecraft/client/multiplayer/MultiPlayerGameMode.getPlayerMode:()Lnet/minecraft/world/level/GameType;
     148: getstatic     #637                // Field net/minecraft/world/level/GameType.SPECTATOR:Lnet/minecraft/world/level/GameType;
     151: if_acmpeq     199
     154: aload_0
     155: getfield      #122                // Field itemInHandRenderer:Lnet/minecraft/client/renderer/ItemInHandRenderer;
     158: fload_2
     159: aload         4
     161: aload_0
     162: getfield      #118                // Field minecraft:Lnet/minecraft/client/Minecraft;
     165: getfield      #643                // Field net/minecraft/client/Minecraft.gameRenderer:Lnet/minecraft/client/renderer/GameRenderer;
     168: invokevirtual #647                // Method getSubmitNodeStorage:()Lnet/minecraft/client/renderer/SubmitNodeStorage;
     171: aload_0
     172: getfield      #118                // Field minecraft:Lnet/minecraft/client/Minecraft;
     175: getfield      #348                // Field net/minecraft/client/Minecraft.player:Lnet/minecraft/client/player/LocalPlayer;
     178: aload_0
     179: getfield      #118                // Field minecraft:Lnet/minecraft/client/Minecraft;
     182: invokevirtual #186                // Method net/minecraft/client/Minecraft.getEntityRenderDispatcher:()Lnet/minecraft/client/renderer/entity/EntityRenderDispatcher;
     185: aload_0
     186: getfield      #118                // Field minecraft:Lnet/minecraft/client/Minecraft;
     189: getfield      #348                // Field net/minecraft/client/Minecraft.player:Lnet/minecraft/client/player/LocalPlayer;
     192: fload_2
     193: invokevirtual #651                // Method net/minecraft/client/renderer/entity/EntityRenderDispatcher.getPackedLightCoords:(Lnet/minecraft/world/entity/Entity;F)I
     196: invokevirtual #657                // Method net/minecraft/client/renderer/ItemInHandRenderer.renderHandsWithItems:(FLcom/mojang/blaze3d/vertex/PoseStack;Lnet/minecraft/client/renderer/SubmitNodeCollector;Lnet/minecraft/client/player/LocalPlayer;I)V
     199: aload         5
     201: invokevirtual #661                // Method org/joml/Matrix4fStack.popMatrix:()Lorg/joml/Matrix4fStack;
     204: pop
     205: aload         4
     207: invokevirtual #664                // Method com/mojang/blaze3d/vertex/PoseStack.popPose:()V
     210: return

  public static float getNightVisionScale(net.minecraft.world.entity.LivingEntity, float);
    Code:
       0: aload_0
       1: getstatic     #667                // Field net/minecraft/world/effect/MobEffects.NIGHT_VISION:Lnet/minecraft/core/Holder;
       4: invokevirtual #670                // Method net/minecraft/world/entity/LivingEntity.getEffect:(Lnet/minecraft/core/Holder;)Lnet/minecraft/world/effect/MobEffectInstance;
       7: astore_2
       8: aload_2
       9: sipush        200
      12: invokevirtual #674                // Method net/minecraft/world/effect/MobEffectInstance.endsWithin:(I)Z
      15: ifne          20
      18: fconst_1
      19: freturn
      20: ldc_w         #680                // float 0.7f
      23: aload_2
      24: invokevirtual #681                // Method net/minecraft/world/effect/MobEffectInstance.getDuration:()I
      27: i2f
      28: fload_1
      29: fsub
      30: ldc_w         #514                // float 3.1415927f
      33: fmul
      34: ldc_w         #562                // float 0.2f
      37: fmul
      38: f2d
      39: invokestatic  #515                // Method net/minecraft/util/Mth.sin:(D)F
      42: ldc_w         #685                // float 0.3f
      45: fmul
      46: fadd
      47: freturn

  public void update(net.minecraft.client.DeltaTracker, boolean);
    Code:
       0: invokestatic  #428                // Method net/minecraft/util/profiling/Profiler.get:()Lnet/minecraft/util/profiling/ProfilerFiller;
       3: astore_3
       4: aload_3
       5: ldc_w         #686                // String camera
       8: invokeinterface #435,  2          // InterfaceMethod net/minecraft/util/profiling/ProfilerFiller.push:(Ljava/lang/String;)V
      13: aload_0
      14: getfield      #77                 // Field mainCamera:Lnet/minecraft/client/Camera;
      17: aload_1
      18: invokevirtual #688                // Method net/minecraft/client/Camera.update:(Lnet/minecraft/client/DeltaTracker;)V
      21: aload_3
      22: invokeinterface #448,  1          // InterfaceMethod net/minecraft/util/profiling/ProfilerFiller.pop:()V
      27: aload_0
      28: getfield      #118                // Field minecraft:Lnet/minecraft/client/Minecraft;
      31: invokevirtual #692                // Method net/minecraft/client/Minecraft.isGameLoadFinished:()Z
      34: istore        4
      36: iload         4
      38: ifeq          59
      41: iload_2
      42: ifeq          59
      45: aload_0
      46: getfield      #118                // Field minecraft:Lnet/minecraft/client/Minecraft;
      49: getfield      #388                // Field net/minecraft/client/Minecraft.level:Lnet/minecraft/client/multiplayer/ClientLevel;
      52: ifnull        59
      55: iconst_1
      56: goto          60
      59: iconst_0
      60: istore        5
      62: iload         5
      64: ifeq          81
      67: aload_0
      68: getfield      #118                // Field minecraft:Lnet/minecraft/client/Minecraft;
      71: getfield      #440                // Field net/minecraft/client/Minecraft.levelRenderer:Lnet/minecraft/client/renderer/LevelRenderer;
      74: aload_0
      75: getfield      #77                 // Field mainCamera:Lnet/minecraft/client/Camera;
      78: invokevirtual #695                // Method net/minecraft/client/renderer/LevelRenderer.update:(Lnet/minecraft/client/Camera;)V
      81: return

  public void extract(net.minecraft.client.DeltaTracker, boolean);
    Code:
       0: aload_0
       1: getfield      #118                // Field minecraft:Lnet/minecraft/client/Minecraft;
       4: invokevirtual #692                // Method net/minecraft/client/Minecraft.isGameLoadFinished:()Z
       7: istore_3
       8: iload_3
       9: ifeq          30
      12: iload_2
      13: ifeq          30
      16: aload_0
      17: getfield      #118                // Field minecraft:Lnet/minecraft/client/Minecraft;
      20: getfield      #388                // Field net/minecraft/client/Minecraft.level:Lnet/minecraft/client/multiplayer/ClientLevel;
      23: ifnull        30
      26: iconst_1
      27: goto          31
      30: iconst_0
      31: istore        4
      33: aload_1
      34: iconst_0
      35: invokeinterface #697,  2          // InterfaceMethod net/minecraft/client/DeltaTracker.getGameTimeDeltaPartialTick:(Z)F
      40: fstore        5
      42: aload_0
      43: invokevirtual #703                // Method extractWindow:()V
      46: aload_0
      47: invokevirtual #706                // Method extractOptions:()V
      50: iload         4
      52: ifeq          106
      55: aload_0
      56: getfield      #131                // Field lightmapRenderStateExtractor:Lnet/minecraft/client/renderer/LightmapRenderStateExtractor;
      59: aload_0
      60: getfield      #10                 // Field gameRenderState:Lnet/minecraft/client/renderer/state/GameRenderState;
      63: getfield      #709                // Field net/minecraft/client/renderer/state/GameRenderState.lightmapRenderState:Lnet/minecraft/client/renderer/state/LightmapRenderState;
      66: fconst_1
      67: invokevirtual #713                // Method net/minecraft/client/renderer/LightmapRenderStateExtractor.extract:(Lnet/minecraft/client/renderer/state/LightmapRenderState;F)V
      70: aload_0
      71: getfield      #77                 // Field mainCamera:Lnet/minecraft/client/Camera;
      74: aload_1
      75: invokevirtual #717                // Method net/minecraft/client/Camera.getCameraEntityPartialTicks:(Lnet/minecraft/client/DeltaTracker;)F
      78: fstore        6
      80: aload_0
      81: aload_1
      82: fload         5
      84: fload         6
      86: invokevirtual #721                // Method extractCamera:(Lnet/minecraft/client/DeltaTracker;FF)V
      89: aload_0
      90: getfield      #118                // Field minecraft:Lnet/minecraft/client/Minecraft;
      93: getfield      #440                // Field net/minecraft/client/Minecraft.levelRenderer:Lnet/minecraft/client/renderer/LevelRenderer;
      96: aload_1
      97: aload_0
      98: getfield      #77                 // Field mainCamera:Lnet/minecraft/client/Camera;
     101: fload         5
     103: invokevirtual #725                // Method net/minecraft/client/renderer/LevelRenderer.extractLevel:(Lnet/minecraft/client/DeltaTracker;Lnet/minecraft/client/Camera;F)V
     106: aload_0
     107: aload_1
     108: iload         4
     110: iload_3
     111: invokevirtual #729                // Method extractGui:(Lnet/minecraft/client/DeltaTracker;ZZ)V
     114: return

  public void render(net.minecraft.client.DeltaTracker, boolean);
    Code:
       0: invokestatic  #428                // Method net/minecraft/util/profiling/Profiler.get:()Lnet/minecraft/util/profiling/ProfilerFiller;
       3: astore_3
       4: aload_3
       5: ldc_w         #733                // String render
       8: invokeinterface #435,  2          // InterfaceMethod net/minecraft/util/profiling/ProfilerFiller.push:(Ljava/lang/String;)V
      13: aload_0
      14: getfield      #10                 // Field gameRenderState:Lnet/minecraft/client/renderer/state/GameRenderState;
      17: getfield      #735                // Field net/minecraft/client/renderer/state/GameRenderState.windowRenderState:Lnet/minecraft/client/renderer/state/WindowRenderState;
      20: getfield      #739                // Field net/minecraft/client/renderer/state/WindowRenderState.isResized:Z
      23: ifeq          50
      26: aload_0
      27: aload_0
      28: getfield      #10                 // Field gameRenderState:Lnet/minecraft/client/renderer/state/GameRenderState;
      31: getfield      #735                // Field net/minecraft/client/renderer/state/GameRenderState.windowRenderState:Lnet/minecraft/client/renderer/state/WindowRenderState;
      34: getfield      #744                // Field net/minecraft/client/renderer/state/WindowRenderState.width:I
      37: aload_0
      38: getfield      #10                 // Field gameRenderState:Lnet/minecraft/client/renderer/state/GameRenderState;
      41: getfield      #735                // Field net/minecraft/client/renderer/state/GameRenderState.windowRenderState:Lnet/minecraft/client/renderer/state/WindowRenderState;
      44: getfield      #747                // Field net/minecraft/client/renderer/state/WindowRenderState.height:I
      47: invokevirtual #750                // Method resize:(II)V
      50: aload_0
      51: getfield      #118                // Field minecraft:Lnet/minecraft/client/Minecraft;
      54: invokevirtual #301                // Method net/minecraft/client/Minecraft.getMainRenderTarget:()Lcom/mojang/blaze3d/pipeline/RenderTarget;
      57: astore        4
      59: invokestatic  #311                // Method com/mojang/blaze3d/systems/RenderSystem.getDevice:()Lcom/mojang/blaze3d/systems/GpuDevice;
      62: invokevirtual #751                // Method com/mojang/blaze3d/systems/GpuDevice.createCommandEncoder:()Lcom/mojang/blaze3d/systems/CommandEncoder;
      65: aload         4
      67: invokevirtual #755                // Method com/mojang/blaze3d/pipeline/RenderTarget.getColorTexture:()Lcom/mojang/blaze3d/textures/GpuTexture;
      70: aload_0
      71: getfield      #10                 // Field gameRenderState:Lnet/minecraft/client/renderer/state/GameRenderState;
      74: getfield      #180                // Field net/minecraft/client/renderer/state/GameRenderState.guiRenderState:Lnet/minecraft/client/renderer/state/gui/GuiRenderState;
      77: getfield      #759                // Field net/minecraft/client/renderer/state/gui/GuiRenderState.clearColorOverride:I
      80: aload         4
      82: invokevirtual #764                // Method com/mojang/blaze3d/pipeline/RenderTarget.getDepthTexture:()Lcom/mojang/blaze3d/textures/GpuTexture;
      85: dconst_1
      86: invokevirtual #767                // Method com/mojang/blaze3d/systems/CommandEncoder.clearColorAndDepthTextures:(Lcom/mojang/blaze3d/textures/GpuTexture;ILcom/mojang/blaze3d/textures/GpuTexture;D)V
      89: aload_0
      90: getfield      #118                // Field minecraft:Lnet/minecraft/client/Minecraft;
      93: invokevirtual #692                // Method net/minecraft/client/Minecraft.isGameLoadFinished:()Z
      96: istore        5
      98: iload         5
     100: ifeq          121
     103: iload_2
     104: ifeq          121
     107: aload_0
     108: getfield      #118                // Field minecraft:Lnet/minecraft/client/Minecraft;
     111: getfield      #388                // Field net/minecraft/client/Minecraft.level:Lnet/minecraft/client/multiplayer/ClientLevel;
     114: ifnull        121
     117: iconst_1
     118: goto          122
     121: iconst_0
     122: istore        6
     124: aload_0
     125: getfield      #98                 // Field globalSettingsUniform:Lnet/minecraft/client/renderer/GlobalSettingsUniform;
     128: aload_0
     129: getfield      #10                 // Field gameRenderState:Lnet/minecraft/client/renderer/state/GameRenderState;
     132: getfield      #735                // Field net/minecraft/client/renderer/state/GameRenderState.windowRenderState:Lnet/minecraft/client/renderer/state/WindowRenderState;
     135: getfield      #744                // Field net/minecraft/client/renderer/state/WindowRenderState.width:I
     138: aload_0
     139: getfield      #10                 // Field gameRenderState:Lnet/minecraft/client/renderer/state/GameRenderState;
     142: getfield      #735                // Field net/minecraft/client/renderer/state/GameRenderState.windowRenderState:Lnet/minecraft/client/renderer/state/WindowRenderState;
     145: getfield      #747                // Field net/minecraft/client/renderer/state/WindowRenderState.height:I
     148: aload_0
     149: getfield      #10                 // Field gameRenderState:Lnet/minecraft/client/renderer/state/GameRenderState;
     152: getfield      #527                // Field net/minecraft/client/renderer/state/GameRenderState.optionsRenderState:Lnet/minecraft/client/renderer/state/OptionsRenderState;
     155: getfield      #773                // Field net/minecraft/client/renderer/state/OptionsRenderState.glintStrength:D
     158: aload_0
     159: getfield      #118                // Field minecraft:Lnet/minecraft/client/Minecraft;
     162: getfield      #388                // Field net/minecraft/client/Minecraft.level:Lnet/minecraft/client/multiplayer/ClientLevel;
     165: ifnonnull     172
     168: lconst_0
     169: goto          182
     172: aload_0
     173: getfield      #118                // Field minecraft:Lnet/minecraft/client/Minecraft;
     176: getfield      #388                // Field net/minecraft/client/Minecraft.level:Lnet/minecraft/client/multiplayer/ClientLevel;
     179: invokevirtual #776                // Method net/minecraft/client/multiplayer/ClientLevel.getGameTime:()J
     182: aload_1
     183: aload_0
     184: getfield      #10                 // Field gameRenderState:Lnet/minecraft/client/renderer/state/GameRenderState;
     187: getfield      #527                // Field net/minecraft/client/renderer/state/GameRenderState.optionsRenderState:Lnet/minecraft/client/renderer/state/OptionsRenderState;
     190: getfield      #780                // Field net/minecraft/client/renderer/state/OptionsRenderState.menuBackgroundBlurriness:I
     193: aload_0
     194: getfield      #10                 // Field gameRenderState:Lnet/minecraft/client/renderer/state/GameRenderState;
     197: getfield      #783                // Field net/minecraft/client/renderer/state/GameRenderState.levelRenderState:Lnet/minecraft/client/renderer/state/level/LevelRenderState;
     200: getfield      #787                // Field net/minecraft/client/renderer/state/level/LevelRenderState.cameraRenderState:Lnet/minecraft/client/renderer/state/level/CameraRenderState;
     203: getfield      #793                // Field net/minecraft/client/renderer/state/level/CameraRenderState.pos:Lnet/minecraft/world/phys/Vec3;
     206: aload_0
     207: getfield      #10                 // Field gameRenderState:Lnet/minecraft/client/renderer/state/GameRenderState;
     210: getfield      #527                // Field net/minecraft/client/renderer/state/GameRenderState.optionsRenderState:Lnet/minecraft/client/renderer/state/OptionsRenderState;
     213: getfield      #797                // Field net/minecraft/client/renderer/state/OptionsRenderState.textureFiltering:Lnet/minecraft/client/TextureFilteringMethod;
     216: getstatic     #801                // Field net/minecraft/client/TextureFilteringMethod.RGSS:Lnet/minecraft/client/TextureFilteringMethod;
     219: if_acmpne     226
     222: iconst_1
     223: goto          227
     226: iconst_0
     227: invokevirtual #806                // Method net/minecraft/client/renderer/GlobalSettingsUniform.update:(IIDJLnet/minecraft/client/DeltaTracker;ILnet/minecraft/world/phys/Vec3;Z)V
     230: iload         6
     232: ifeq          337
     235: aload_0
     236: getfield      #33                 // Field lightmap:Lnet/minecraft/client/renderer/Lightmap;
     239: aload_0
     240: getfield      #10                 // Field gameRenderState:Lnet/minecraft/client/renderer/state/GameRenderState;
     243: getfield      #709                // Field net/minecraft/client/renderer/state/GameRenderState.lightmapRenderState:Lnet/minecraft/client/renderer/state/LightmapRenderState;
     246: invokevirtual #809                // Method net/minecraft/client/renderer/Lightmap.render:(Lnet/minecraft/client/renderer/state/LightmapRenderState;)V
     249: aload_3
     250: ldc_w         #812                // String world
     253: invokeinterface #435,  2          // InterfaceMethod net/minecraft/util/profiling/ProfilerFiller.push:(Ljava/lang/String;)V
     258: aload_0
     259: aload_1
     260: invokevirtual #814                // Method renderLevel:(Lnet/minecraft/client/DeltaTracker;)V
     263: aload_0
     264: invokevirtual #817                // Method tryTakeScreenshotIfNeeded:()V
     267: aload_0
     268: getfield      #118                // Field minecraft:Lnet/minecraft/client/Minecraft;
     271: getfield      #440                // Field net/minecraft/client/Minecraft.levelRenderer:Lnet/minecraft/client/renderer/LevelRenderer;
     274: invokevirtual #820                // Method net/minecraft/client/renderer/LevelRenderer.doEntityOutline:()V
     277: aload_0
     278: getfield      #246                // Field postEffectId:Lnet/minecraft/resources/Identifier;
     281: ifnull        331
     284: aload_0
     285: getfield      #250                // Field effectActive:Z
     288: ifeq          331
     291: aload_0
     292: getfield      #118                // Field minecraft:Lnet/minecraft/client/Minecraft;
     295: invokevirtual #282                // Method net/minecraft/client/Minecraft.getShaderManager:()Lnet/minecraft/client/renderer/ShaderManager;
     298: aload_0
     299: getfield      #246                // Field postEffectId:Lnet/minecraft/resources/Identifier;
     302: getstatic     #289                // Field net/minecraft/client/renderer/LevelTargetBundle.MAIN_TARGETS:Ljava/util/Set;
     305: invokevirtual #295                // Method net/minecraft/client/renderer/ShaderManager.getPostChain:(Lnet/minecraft/resources/Identifier;Ljava/util/Set;)Lnet/minecraft/client/renderer/PostChain;
     308: astore        7
     310: aload         7
     312: ifnull        331
     315: aload         7
     317: aload_0
     318: getfield      #118                // Field minecraft:Lnet/minecraft/client/Minecraft;
     321: invokevirtual #301                // Method net/minecraft/client/Minecraft.getMainRenderTarget:()Lcom/mojang/blaze3d/pipeline/RenderTarget;
     324: aload_0
     325: getfield      #63                 // Field resourcePool:Lcom/mojang/blaze3d/resource/CrossFrameResourcePool;
     328: invokevirtual #305                // Method net/minecraft/client/renderer/PostChain.process:(Lcom/mojang/blaze3d/pipeline/RenderTarget;Lcom/mojang/blaze3d/resource/GraphicsResourceAllocator;)V
     331: aload_3
     332: invokeinterface #448,  1          // InterfaceMethod net/minecraft/util/profiling/ProfilerFiller.pop:()V
     337: aload_0
     338: getfield      #70                 // Field fogRenderer:Lnet/minecraft/client/renderer/fog/FogRenderer;
     341: invokevirtual #823                // Method net/minecraft/client/renderer/fog/FogRenderer.endFrame:()V
     344: invokestatic  #311                // Method com/mojang/blaze3d/systems/RenderSystem.getDevice:()Lcom/mojang/blaze3d/systems/GpuDevice;
     347: invokevirtual #751                // Method com/mojang/blaze3d/systems/GpuDevice.createCommandEncoder:()Lcom/mojang/blaze3d/systems/CommandEncoder;
     350: aload         4
     352: invokevirtual #764                // Method com/mojang/blaze3d/pipeline/RenderTarget.getDepthTexture:()Lcom/mojang/blaze3d/textures/GpuTexture;
     355: dconst_1
     356: invokevirtual #826                // Method com/mojang/blaze3d/systems/CommandEncoder.clearDepthTexture:(Lcom/mojang/blaze3d/textures/GpuTexture;D)V
     359: aload_0
     360: invokevirtual #830                // Method getLighting:()Lcom/mojang/blaze3d/platform/Lighting;
     363: getstatic     #834                // Field com/mojang/blaze3d/platform/Lighting$Entry.ITEMS_3D:Lcom/mojang/blaze3d/platform/Lighting$Entry;
     366: invokevirtual #840                // Method com/mojang/blaze3d/platform/Lighting.setupFor:(Lcom/mojang/blaze3d/platform/Lighting$Entry;)V
     369: aload_0
     370: iconst_1
     371: putfield      #844                // Field useUiLightmap:Z
     374: aload_3
     375: ldc_w         #847                // String gui
     378: invokeinterface #435,  2          // InterfaceMethod net/minecraft/util/profiling/ProfilerFiller.push:(Ljava/lang/String;)V
     383: aload_0
     384: getfield      #221                // Field guiRenderer:Lnet/minecraft/client/gui/render/GuiRenderer;
     387: aload_0
     388: getfield      #70                 // Field fogRenderer:Lnet/minecraft/client/renderer/fog/FogRenderer;
     391: getstatic     #848                // Field net/minecraft/client/renderer/fog/FogRenderer$FogMode.NONE:Lnet/minecraft/client/renderer/fog/FogRenderer$FogMode;
     394: invokevirtual #854                // Method net/minecraft/client/renderer/fog/FogRenderer.getBuffer:(Lnet/minecraft/client/renderer/fog/FogRenderer$FogMode;)Lcom/mojang/blaze3d/buffers/GpuBufferSlice;
     397: invokevirtual #858                // Method net/minecraft/client/gui/render/GuiRenderer.render:(Lcom/mojang/blaze3d/buffers/GpuBufferSlice;)V
     400: aload_0
     401: getfield      #221                // Field guiRenderer:Lnet/minecraft/client/gui/render/GuiRenderer;
     404: invokevirtual #861                // Method net/minecraft/client/gui/render/GuiRenderer.endFrame:()V
     407: aload_3
     408: invokeinterface #448,  1          // InterfaceMethod net/minecraft/util/profiling/ProfilerFiller.pop:()V
     413: aload_0
     414: iconst_0
     415: putfield      #844                // Field useUiLightmap:Z
     418: aload_0
     419: getfield      #154                // Field submitNodeStorage:Lnet/minecraft/client/renderer/SubmitNodeStorage;
     422: invokevirtual #862                // Method net/minecraft/client/renderer/SubmitNodeStorage.endFrame:()V
     425: aload_0
     426: getfield      #174                // Field featureRenderDispatcher:Lnet/minecraft/client/renderer/feature/FeatureRenderDispatcher;
     429: invokevirtual #863                // Method net/minecraft/client/renderer/feature/FeatureRenderDispatcher.endFrame:()V
     432: aload_0
     433: getfield      #63                 // Field resourcePool:Lcom/mojang/blaze3d/resource/CrossFrameResourcePool;
     436: invokevirtual #864                // Method com/mojang/blaze3d/resource/CrossFrameResourcePool.endFrame:()V
     439: aload_3
     440: invokeinterface #448,  1          // InterfaceMethod net/minecraft/util/profiling/ProfilerFiller.pop:()V
     445: return

  private void extractGui(net.minecraft.client.DeltaTracker, boolean, boolean);
    Code:
       0: invokestatic  #428                // Method net/minecraft/util/profiling/Profiler.get:()Lnet/minecraft/util/profiling/ProfilerFiller;
       3: astore        4
       5: aload_0
       6: getfield      #118                // Field minecraft:Lnet/minecraft/client/Minecraft;
       9: getfield      #865                // Field net/minecraft/client/Minecraft.mouseHandler:Lnet/minecraft/client/MouseHandler;
      12: aload_0
      13: getfield      #118                // Field minecraft:Lnet/minecraft/client/Minecraft;
      16: invokevirtual #869                // Method net/minecraft/client/Minecraft.getWindow:()Lcom/mojang/blaze3d/platform/Window;
      19: invokevirtual #873                // Method net/minecraft/client/MouseHandler.getScaledXPos:(Lcom/mojang/blaze3d/platform/Window;)D
      22: d2i
      23: istore        5
      25: aload_0
      26: getfield      #118                // Field minecraft:Lnet/minecraft/client/Minecraft;
      29: getfield      #865                // Field net/minecraft/client/Minecraft.mouseHandler:Lnet/minecraft/client/MouseHandler;
      32: aload_0
      33: getfield      #118                // Field minecraft:Lnet/minecraft/client/Minecraft;
      36: invokevirtual #869                // Method net/minecraft/client/Minecraft.getWindow:()Lcom/mojang/blaze3d/platform/Window;
      39: invokevirtual #879                // Method net/minecraft/client/MouseHandler.getScaledYPos:(Lcom/mojang/blaze3d/platform/Window;)D
      42: d2i
      43: istore        6
      45: aload         4
      47: ldc_w         #847                // String gui
      50: invokeinterface #435,  2          // InterfaceMethod net/minecraft/util/profiling/ProfilerFiller.push:(Ljava/lang/String;)V
      55: aload_0
      56: getfield      #10                 // Field gameRenderState:Lnet/minecraft/client/renderer/state/GameRenderState;
      59: getfield      #180                // Field net/minecraft/client/renderer/state/GameRenderState.guiRenderState:Lnet/minecraft/client/renderer/state/gui/GuiRenderState;
      62: invokevirtual #882                // Method net/minecraft/client/renderer/state/gui/GuiRenderState.reset:()V
      65: new           #885                // class net/minecraft/client/gui/GuiGraphicsExtractor
      68: dup
      69: aload_0
      70: getfield      #118                // Field minecraft:Lnet/minecraft/client/Minecraft;
      73: aload_0
      74: getfield      #10                 // Field gameRenderState:Lnet/minecraft/client/renderer/state/GameRenderState;
      77: getfield      #180                // Field net/minecraft/client/renderer/state/GameRenderState.guiRenderState:Lnet/minecraft/client/renderer/state/gui/GuiRenderState;
      80: iload         5
      82: iload         6
      84: invokespecial #887                // Method net/minecraft/client/gui/GuiGraphicsExtractor."<init>":(Lnet/minecraft/client/Minecraft;Lnet/minecraft/client/renderer/state/gui/GuiRenderState;II)V
      87: astore        7
      89: iload_2
      90: ifeq          123
      93: aload         4
      95: ldc_w         #890                // String inGameGui
      98: invokeinterface #435,  2          // InterfaceMethod net/minecraft/util/profiling/ProfilerFiller.push:(Ljava/lang/String;)V
     103: aload_0
     104: getfield      #118                // Field minecraft:Lnet/minecraft/client/Minecraft;
     107: getfield      #408                // Field net/minecraft/client/Minecraft.gui:Lnet/minecraft/client/gui/Gui;
     110: aload         7
     112: aload_1
     113: invokevirtual #892                // Method net/minecraft/client/gui/Gui.extractRenderState:(Lnet/minecraft/client/gui/GuiGraphicsExtractor;Lnet/minecraft/client/DeltaTracker;)V
     116: aload         4
     118: invokeinterface #448,  1          // InterfaceMethod net/minecraft/util/profiling/ProfilerFiller.pop:()V
     123: aload_0
     124: getfield      #118                // Field minecraft:Lnet/minecraft/client/Minecraft;
     127: invokevirtual #896                // Method net/minecraft/client/Minecraft.getOverlay:()Lnet/minecraft/client/gui/screens/Overlay;
     130: ifnull        225
     133: aload         4
     135: ldc_w         #900                // String overlay
     138: invokeinterface #435,  2          // InterfaceMethod net/minecraft/util/profiling/ProfilerFiller.push:(Ljava/lang/String;)V
     143: aload_0
     144: getfield      #118                // Field minecraft:Lnet/minecraft/client/Minecraft;
     147: invokevirtual #896                // Method net/minecraft/client/Minecraft.getOverlay:()Lnet/minecraft/client/gui/screens/Overlay;
     150: aload         7
     152: iload         5
     154: iload         6
     156: aload_1
     157: invokeinterface #902,  1          // InterfaceMethod net/minecraft/client/DeltaTracker.getGameTimeDeltaTicks:()F
     162: invokevirtual #906                // Method net/minecraft/client/gui/screens/Overlay.extractRenderState:(Lnet/minecraft/client/gui/GuiGraphicsExtractor;IIF)V
     165: goto          215
     168: astore        8
     170: aload         8
     172: ldc_w         #913                // String Extracting overlay render state
     175: invokestatic  #915                // Method net/minecraft/CrashReport.forThrowable:(Ljava/lang/Throwable;Ljava/lang/String;)Lnet/minecraft/CrashReport;
     178: astore        9
     180: aload         9
     182: ldc_w         #921                // String Overlay details
     185: invokevirtual #923                // Method net/minecraft/CrashReport.addCategory:(Ljava/lang/String;)Lnet/minecraft/CrashReportCategory;
     188: astore        10
     190: aload         10
     192: ldc_w         #927                // String Overlay name
     195: aload_0
     196: invokedynamic #929,  0            // InvokeDynamic #2:call:(Lnet/minecraft/client/renderer/GameRenderer;)Lnet/minecraft/CrashReportDetail;
     201: invokevirtual #933                // Method net/minecraft/CrashReportCategory.setDetail:(Ljava/lang/String;Lnet/minecraft/CrashReportDetail;)Lnet/minecraft/CrashReportCategory;
     204: pop
     205: new           #939                // class net/minecraft/ReportedException
     208: dup
     209: aload         9
     211: invokespecial #941                // Method net/minecraft/ReportedException."<init>":(Lnet/minecraft/CrashReport;)V
     214: athrow
     215: aload         4
     217: invokeinterface #448,  1          // InterfaceMethod net/minecraft/util/profiling/ProfilerFiller.pop:()V
     222: goto          442
     225: iload_3
     226: ifeq          442
     229: aload_0
     230: getfield      #118                // Field minecraft:Lnet/minecraft/client/Minecraft;
     233: getfield      #944                // Field net/minecraft/client/Minecraft.screen:Lnet/minecraft/client/gui/screens/Screen;
     236: ifnull        442
     239: aload         4
     241: ldc_w         #948                // String screen
     244: invokeinterface #435,  2          // InterfaceMethod net/minecraft/util/profiling/ProfilerFiller.push:(Ljava/lang/String;)V
     249: aload_0
     250: getfield      #118                // Field minecraft:Lnet/minecraft/client/Minecraft;
     253: getfield      #944                // Field net/minecraft/client/Minecraft.screen:Lnet/minecraft/client/gui/screens/Screen;
     256: aload         7
     258: iload         5
     260: iload         6
     262: aload_1
     263: invokeinterface #902,  1          // InterfaceMethod net/minecraft/client/DeltaTracker.getGameTimeDeltaTicks:()F
     268: invokevirtual #949                // Method net/minecraft/client/gui/screens/Screen.extractRenderStateWithTooltipAndSubtitles:(Lnet/minecraft/client/gui/GuiGraphicsExtractor;IIF)V
     271: goto          340
     274: astore        8
     276: aload         8
     278: ldc_w         #954                // String Rendering screen
     281: invokestatic  #915                // Method net/minecraft/CrashReport.forThrowable:(Ljava/lang/Throwable;Ljava/lang/String;)Lnet/minecraft/CrashReport;
     284: astore        9
     286: aload         9
     288: ldc_w         #956                // String Screen render details
     291: invokevirtual #923                // Method net/minecraft/CrashReport.addCategory:(Ljava/lang/String;)Lnet/minecraft/CrashReportCategory;
     294: astore        10
     296: aload         10
     298: ldc_w         #958                // String Screen name
     301: aload_0
     302: invokedynamic #960,  0            // InvokeDynamic #3:call:(Lnet/minecraft/client/renderer/GameRenderer;)Lnet/minecraft/CrashReportDetail;
     307: invokevirtual #933                // Method net/minecraft/CrashReportCategory.setDetail:(Ljava/lang/String;Lnet/minecraft/CrashReportDetail;)Lnet/minecraft/CrashReportCategory;
     310: pop
     311: aload_0
     312: getfield      #118                // Field minecraft:Lnet/minecraft/client/Minecraft;
     315: getfield      #865                // Field net/minecraft/client/Minecraft.mouseHandler:Lnet/minecraft/client/MouseHandler;
     318: aload         10
     320: aload_0
     321: getfield      #118                // Field minecraft:Lnet/minecraft/client/Minecraft;
     324: invokevirtual #869                // Method net/minecraft/client/Minecraft.getWindow:()Lcom/mojang/blaze3d/platform/Window;
     327: invokevirtual #961                // Method net/minecraft/client/MouseHandler.fillMousePositionDetails:(Lnet/minecraft/CrashReportCategory;Lcom/mojang/blaze3d/platform/Window;)V
     330: new           #939                // class net/minecraft/ReportedException
     333: dup
     334: aload         9
     336: invokespecial #941                // Method net/minecraft/ReportedException."<init>":(Lnet/minecraft/CrashReport;)V
     339: athrow
     340: getstatic     #965                // Field net/minecraft/SharedConstants.DEBUG_CURSOR_POS:Z
     343: ifeq          365
     346: aload_0
     347: getfield      #118                // Field minecraft:Lnet/minecraft/client/Minecraft;
     350: getfield      #865                // Field net/minecraft/client/Minecraft.mouseHandler:Lnet/minecraft/client/MouseHandler;
     353: aload_0
     354: getfield      #118                // Field minecraft:Lnet/minecraft/client/Minecraft;
     357: getfield      #167                // Field net/minecraft/client/Minecraft.font:Lnet/minecraft/client/gui/Font;
     360: aload         7
     362: invokevirtual #968                // Method net/minecraft/client/MouseHandler.drawDebugMouseInfo:(Lnet/minecraft/client/gui/Font;Lnet/minecraft/client/gui/GuiGraphicsExtractor;)V
     365: aload_0
     366: getfield      #118                // Field minecraft:Lnet/minecraft/client/Minecraft;
     369: getfield      #944                // Field net/minecraft/client/Minecraft.screen:Lnet/minecraft/client/gui/screens/Screen;
     372: ifnull        385
     375: aload_0
     376: getfield      #118                // Field minecraft:Lnet/minecraft/client/Minecraft;
     379: getfield      #944                // Field net/minecraft/client/Minecraft.screen:Lnet/minecraft/client/gui/screens/Screen;
     382: invokevirtual #972                // Method net/minecraft/client/gui/screens/Screen.handleDelayedNarration:()V
     385: goto          435
     388: astore        8
     390: aload         8
     392: ldc_w         #975                // String Narrating screen
     395: invokestatic  #915                // Method net/minecraft/CrashReport.forThrowable:(Ljava/lang/Throwable;Ljava/lang/String;)Lnet/minecraft/CrashReport;
     398: astore        9
     400: aload         9
     402: ldc_w         #977                // String Screen details
     405: invokevirtual #923                // Method net/minecraft/CrashReport.addCategory:(Ljava/lang/String;)Lnet/minecraft/CrashReportCategory;
     408: astore        10
     410: aload         10
     412: ldc_w         #958                // String Screen name
     415: aload_0
     416: invokedynamic #979,  0            // InvokeDynamic #4:call:(Lnet/minecraft/client/renderer/GameRenderer;)Lnet/minecraft/CrashReportDetail;
     421: invokevirtual #933                // Method net/minecraft/CrashReportCategory.setDetail:(Ljava/lang/String;Lnet/minecraft/CrashReportDetail;)Lnet/minecraft/CrashReportCategory;
     424: pop
     425: new           #939                // class net/minecraft/ReportedException
     428: dup
     429: aload         9
     431: invokespecial #941                // Method net/minecraft/ReportedException."<init>":(Lnet/minecraft/CrashReport;)V
     434: athrow
     435: aload         4
     437: invokeinterface #448,  1          // InterfaceMethod net/minecraft/util/profiling/ProfilerFiller.pop:()V
     442: iload_2
     443: ifeq          459
     446: aload_0
     447: getfield      #118                // Field minecraft:Lnet/minecraft/client/Minecraft;
     450: getfield      #408                // Field net/minecraft/client/Minecraft.gui:Lnet/minecraft/client/gui/Gui;
     453: aload         7
     455: aload_1
     456: invokevirtual #980                // Method net/minecraft/client/gui/Gui.extractSavingIndicator:(Lnet/minecraft/client/gui/GuiGraphicsExtractor;Lnet/minecraft/client/DeltaTracker;)V
     459: iload_3
     460: ifeq          527
     463: aload         4
     465: ldc_w         #983                // String toasts
     468: invokeinterface #985,  2          // InterfaceMethod net/minecraft/util/profiling/ProfilerFiller.zone:(Ljava/lang/String;)Lnet/minecraft/util/profiling/Zone;
     473: astore        8
     475: aload_0
     476: getfield      #118                // Field minecraft:Lnet/minecraft/client/Minecraft;
     479: invokevirtual #989                // Method net/minecraft/client/Minecraft.getToastManager:()Lnet/minecraft/client/gui/components/toasts/ToastManager;
     482: aload         7
     484: invokevirtual #993                // Method net/minecraft/client/gui/components/toasts/ToastManager.extractRenderState:(Lnet/minecraft/client/gui/GuiGraphicsExtractor;)V
     487: aload         8
     489: ifnull        527
     492: aload         8
     494: invokevirtual #998                // Method net/minecraft/util/profiling/Zone.close:()V
     497: goto          527
     500: astore        9
     502: aload         8
     504: ifnull        524
     507: aload         8
     509: invokevirtual #998                // Method net/minecraft/util/profiling/Zone.close:()V
     512: goto          524
     515: astore        10
     517: aload         9
     519: aload         10
     521: invokevirtual #1001               // Method java/lang/Throwable.addSuppressed:(Ljava/lang/Throwable;)V
     524: aload         9
     526: athrow
     527: aload_0
     528: getfield      #118                // Field minecraft:Lnet/minecraft/client/Minecraft;
     531: getfield      #944                // Field net/minecraft/client/Minecraft.screen:Lnet/minecraft/client/gui/screens/Screen;
     534: instanceof    #1005               // class net/minecraft/client/gui/screens/debug/DebugOptionsScreen
     537: ifne          552
     540: aload_0
     541: getfield      #118                // Field minecraft:Lnet/minecraft/client/Minecraft;
     544: getfield      #408                // Field net/minecraft/client/Minecraft.gui:Lnet/minecraft/client/gui/Gui;
     547: aload         7
     549: invokevirtual #1007               // Method net/minecraft/client/gui/Gui.extractDebugOverlay:(Lnet/minecraft/client/gui/GuiGraphicsExtractor;)V
     552: aload_0
     553: getfield      #118                // Field minecraft:Lnet/minecraft/client/Minecraft;
     556: getfield      #408                // Field net/minecraft/client/Minecraft.gui:Lnet/minecraft/client/gui/Gui;
     559: invokevirtual #1010               // Method net/minecraft/client/gui/Gui.extractDeferredSubtitles:()V
     562: getstatic     #1013               // Field net/minecraft/SharedConstants.DEBUG_ACTIVE_TEXT_AREAS:Z
     565: ifeq          572
     568: aload_0
     569: invokevirtual #1016               // Method renderActiveTextDebug:()V
     572: aload         4
     574: invokeinterface #448,  1          // InterfaceMethod net/minecraft/util/profiling/ProfilerFiller.pop:()V
     579: aload         7
     581: aload_0
     582: getfield      #118                // Field minecraft:Lnet/minecraft/client/Minecraft;
     585: invokevirtual #869                // Method net/minecraft/client/Minecraft.getWindow:()Lcom/mojang/blaze3d/platform/Window;
     588: invokevirtual #1019               // Method net/minecraft/client/gui/GuiGraphicsExtractor.applyCursor:(Lcom/mojang/blaze3d/platform/Window;)V
     591: return
    Exception table:
       from    to  target type
         143   165   168   Class java/lang/Throwable
         249   271   274   Class java/lang/Throwable
         365   385   388   Class java/lang/Throwable
         475   487   500   Class java/lang/Throwable
         507   512   515   Class java/lang/Throwable

  private void renderActiveTextDebug();
    Code:
       0: aload_0
       1: getfield      #10                 // Field gameRenderState:Lnet/minecraft/client/renderer/state/GameRenderState;
       4: getfield      #180                // Field net/minecraft/client/renderer/state/GameRenderState.guiRenderState:Lnet/minecraft/client/renderer/state/gui/GuiRenderState;
       7: astore_1
       8: aload_1
       9: invokevirtual #1023               // Method net/minecraft/client/renderer/state/gui/GuiRenderState.nextStratum:()V
      12: aload_1
      13: aload_0
      14: aload_1
      15: invokedynamic #1026,  0           // InvokeDynamic #5:accept:(Lnet/minecraft/client/renderer/GameRenderer;Lnet/minecraft/client/renderer/state/gui/GuiRenderState;)Ljava/util/function/Consumer;
      20: invokevirtual #1030               // Method net/minecraft/client/renderer/state/gui/GuiRenderState.forEachText:(Ljava/util/function/Consumer;)V
      23: return

  private void tryTakeScreenshotIfNeeded();
    Code:
       0: aload_0
       1: getfield      #1034               // Field hasWorldScreenshot:Z
       4: ifne          17
       7: aload_0
       8: getfield      #118                // Field minecraft:Lnet/minecraft/client/Minecraft;
      11: invokevirtual #1037               // Method net/minecraft/client/Minecraft.isLocalServer:()Z
      14: ifne          18
      17: return
      18: invokestatic  #1040               // Method net/minecraft/util/Util.getMillis:()J
      21: lstore_1
      22: lload_1
      23: aload_0
      24: getfield      #1045               // Field lastScreenshotAttempt:J
      27: lsub
      28: ldc2_w        #1049               // long 1000l
      31: lcmp
      32: ifge          36
      35: return
      36: aload_0
      37: lload_1
      38: putfield      #1045               // Field lastScreenshotAttempt:J
      41: aload_0
      42: getfield      #118                // Field minecraft:Lnet/minecraft/client/Minecraft;
      45: invokevirtual #1051               // Method net/minecraft/client/Minecraft.getSingleplayerServer:()Lnet/minecraft/client/server/IntegratedServer;
      48: astore_3
      49: aload_3
      50: ifnull        60
      53: aload_3
      54: invokevirtual #1055               // Method net/minecraft/client/server/IntegratedServer.isStopped:()Z
      57: ifeq          61
      60: return
      61: aload_3
      62: invokevirtual #1060               // Method net/minecraft/client/server/IntegratedServer.getWorldScreenshotFile:()Ljava/util/Optional;
      65: aload_0
      66: invokedynamic #1064,  0           // InvokeDynamic #6:accept:(Lnet/minecraft/client/renderer/GameRenderer;)Ljava/util/function/Consumer;
      71: invokevirtual #1067               // Method java/util/Optional.ifPresent:(Ljava/util/function/Consumer;)V
      74: return

  private void takeAutoScreenshot(java.nio.file.Path);
    Code:
       0: aload_0
       1: getfield      #118                // Field minecraft:Lnet/minecraft/client/Minecraft;
       4: getfield      #440                // Field net/minecraft/client/Minecraft.levelRenderer:Lnet/minecraft/client/renderer/LevelRenderer;
       7: invokevirtual #1072               // Method net/minecraft/client/renderer/LevelRenderer.countRenderedSections:()I
      10: bipush        10
      12: if_icmple     44
      15: aload_0
      16: getfield      #118                // Field minecraft:Lnet/minecraft/client/Minecraft;
      19: getfield      #440                // Field net/minecraft/client/Minecraft.levelRenderer:Lnet/minecraft/client/renderer/LevelRenderer;
      22: invokevirtual #1075               // Method net/minecraft/client/renderer/LevelRenderer.hasRenderedAllSections:()Z
      25: ifeq          44
      28: aload_0
      29: getfield      #118                // Field minecraft:Lnet/minecraft/client/Minecraft;
      32: invokevirtual #301                // Method net/minecraft/client/Minecraft.getMainRenderTarget:()Lcom/mojang/blaze3d/pipeline/RenderTarget;
      35: aload_1
      36: invokedynamic #1078,  0           // InvokeDynamic #7:accept:(Ljava/nio/file/Path;)Ljava/util/function/Consumer;
      41: invokestatic  #1081               // Method net/minecraft/client/Screenshot.takeScreenshot:(Lcom/mojang/blaze3d/pipeline/RenderTarget;Ljava/util/function/Consumer;)V
      44: return

  private boolean shouldRenderBlockOutline();
    Code:
       0: aload_0
       1: getfield      #26                 // Field renderBlockOutline:Z
       4: ifne          9
       7: iconst_0
       8: ireturn
       9: aload_0
      10: getfield      #118                // Field minecraft:Lnet/minecraft/client/Minecraft;
      13: invokevirtual #1087               // Method net/minecraft/client/Minecraft.getCameraEntity:()Lnet/minecraft/world/entity/Entity;
      16: astore_1
      17: aload_1
      18: instanceof    #1090               // class net/minecraft/world/entity/player/Player
      21: ifeq          41
      24: aload_0
      25: getfield      #118                // Field minecraft:Lnet/minecraft/client/Minecraft;
      28: getfield      #1092               // Field net/minecraft/client/Minecraft.options:Lnet/minecraft/client/Options;
      31: getfield      #1096               // Field net/minecraft/client/Options.hideGui:Z
      34: ifne          41
      37: iconst_1
      38: goto          42
      41: iconst_0
      42: istore_2
      43: iload_2
      44: ifeq          229
      47: aload_1
      48: checkcast     #1090               // class net/minecraft/world/entity/player/Player
      51: invokevirtual #1099               // Method net/minecraft/world/entity/player/Player.getAbilities:()Lnet/minecraft/world/entity/player/Abilities;
      54: getfield      #1103               // Field net/minecraft/world/entity/player/Abilities.mayBuild:Z
      57: ifne          229
      60: aload_1
      61: checkcast     #481                // class net/minecraft/world/entity/LivingEntity
      64: invokevirtual #1108               // Method net/minecraft/world/entity/LivingEntity.getMainHandItem:()Lnet/minecraft/world/item/ItemStack;
      67: astore_3
      68: aload_0
      69: getfield      #118                // Field minecraft:Lnet/minecraft/client/Minecraft;
      72: getfield      #1112               // Field net/minecraft/client/Minecraft.hitResult:Lnet/minecraft/world/phys/HitResult;
      75: astore        4
      77: aload         4
      79: ifnull        229
      82: aload         4
      84: invokevirtual #1116               // Method net/minecraft/world/phys/HitResult.getType:()Lnet/minecraft/world/phys/HitResult$Type;
      87: getstatic     #1122               // Field net/minecraft/world/phys/HitResult$Type.BLOCK:Lnet/minecraft/world/phys/HitResult$Type;
      90: if_acmpne     229
      93: aload         4
      95: checkcast     #1128               // class net/minecraft/world/phys/BlockHitResult
      98: invokevirtual #1130               // Method net/minecraft/world/phys/BlockHitResult.getBlockPos:()Lnet/minecraft/core/BlockPos;
     101: astore        5
     103: aload_0
     104: getfield      #118                // Field minecraft:Lnet/minecraft/client/Minecraft;
     107: getfield      #388                // Field net/minecraft/client/Minecraft.level:Lnet/minecraft/client/multiplayer/ClientLevel;
     110: aload         5
     112: invokevirtual #1134               // Method net/minecraft/client/multiplayer/ClientLevel.getBlockState:(Lnet/minecraft/core/BlockPos;)Lnet/minecraft/world/level/block/state/BlockState;
     115: astore        6
     117: aload_0
     118: getfield      #118                // Field minecraft:Lnet/minecraft/client/Minecraft;
     121: getfield      #627                // Field net/minecraft/client/Minecraft.gameMode:Lnet/minecraft/client/multiplayer/MultiPlayerGameMode;
     124: invokevirtual #631                // Method net/minecraft/client/multiplayer/MultiPlayerGameMode.getPlayerMode:()Lnet/minecraft/world/level/GameType;
     127: getstatic     #637                // Field net/minecraft/world/level/GameType.SPECTATOR:Lnet/minecraft/world/level/GameType;
     130: if_acmpne     159
     133: aload         6
     135: aload_0
     136: getfield      #118                // Field minecraft:Lnet/minecraft/client/Minecraft;
     139: getfield      #388                // Field net/minecraft/client/Minecraft.level:Lnet/minecraft/client/multiplayer/ClientLevel;
     142: aload         5
     144: invokevirtual #1138               // Method net/minecraft/world/level/block/state/BlockState.getMenuProvider:(Lnet/minecraft/world/level/Level;Lnet/minecraft/core/BlockPos;)Lnet/minecraft/world/MenuProvider;
     147: ifnull        154
     150: iconst_1
     151: goto          155
     154: iconst_0
     155: istore_2
     156: goto          229
     159: new           #1144               // class net/minecraft/world/level/block/state/pattern/BlockInWorld
     162: dup
     163: aload_0
     164: getfield      #118                // Field minecraft:Lnet/minecraft/client/Minecraft;
     167: getfield      #388                // Field net/minecraft/client/Minecraft.level:Lnet/minecraft/client/multiplayer/ClientLevel;
     170: aload         5
     172: iconst_0
     173: invokespecial #1146               // Method net/minecraft/world/level/block/state/pattern/BlockInWorld."<init>":(Lnet/minecraft/world/level/LevelReader;Lnet/minecraft/core/BlockPos;Z)V
     176: astore        7
     178: aload_0
     179: getfield      #118                // Field minecraft:Lnet/minecraft/client/Minecraft;
     182: getfield      #388                // Field net/minecraft/client/Minecraft.level:Lnet/minecraft/client/multiplayer/ClientLevel;
     185: invokevirtual #1149               // Method net/minecraft/client/multiplayer/ClientLevel.registryAccess:()Lnet/minecraft/core/RegistryAccess;
     188: getstatic     #1153               // Field net/minecraft/core/registries/Registries.BLOCK:Lnet/minecraft/resources/ResourceKey;
     191: invokeinterface #1158,  2         // InterfaceMethod net/minecraft/core/RegistryAccess.lookupOrThrow:(Lnet/minecraft/resources/ResourceKey;)Lnet/minecraft/core/Registry;
     196: astore        8
     198: aload_3
     199: invokevirtual #1164               // Method net/minecraft/world/item/ItemStack.isEmpty:()Z
     202: ifne          227
     205: aload_3
     206: aload         7
     208: invokevirtual #1169               // Method net/minecraft/world/item/ItemStack.canBreakBlockInAdventureMode:(Lnet/minecraft/world/level/block/state/pattern/BlockInWorld;)Z
     211: ifne          223
     214: aload_3
     215: aload         7
     217: invokevirtual #1173               // Method net/minecraft/world/item/ItemStack.canPlaceOnBlockInAdventureMode:(Lnet/minecraft/world/level/block/state/pattern/BlockInWorld;)Z
     220: ifeq          227
     223: iconst_1
     224: goto          228
     227: iconst_0
     228: istore_2
     229: iload_2
     230: ireturn

  public void renderLevel(net.minecraft.client.DeltaTracker);
    Code:
       0: aload_1
       1: iconst_0
       2: invokeinterface #697,  2          // InterfaceMethod net/minecraft/client/DeltaTracker.getGameTimeDeltaPartialTick:(Z)F
       7: fstore_2
       8: aload_0
       9: getfield      #77                 // Field mainCamera:Lnet/minecraft/client/Camera;
      12: aload_1
      13: invokevirtual #717                // Method net/minecraft/client/Camera.getCameraEntityPartialTicks:(Lnet/minecraft/client/DeltaTracker;)F
      16: fstore_3
      17: aload_0
      18: getfield      #118                // Field minecraft:Lnet/minecraft/client/Minecraft;
      21: getfield      #348                // Field net/minecraft/client/Minecraft.player:Lnet/minecraft/client/player/LocalPlayer;
      24: astore        4
      26: invokestatic  #428                // Method net/minecraft/util/profiling/Profiler.get:()Lnet/minecraft/util/profiling/ProfilerFiller;
      29: astore        5
      31: aload_0
      32: invokevirtual #1176               // Method shouldRenderBlockOutline:()Z
      35: istore        6
      37: aload_0
      38: getfield      #10                 // Field gameRenderState:Lnet/minecraft/client/renderer/state/GameRenderState;
      41: getfield      #527                // Field net/minecraft/client/renderer/state/GameRenderState.optionsRenderState:Lnet/minecraft/client/renderer/state/OptionsRenderState;
      44: astore        7
      46: aload_0
      47: getfield      #10                 // Field gameRenderState:Lnet/minecraft/client/renderer/state/GameRenderState;
      50: getfield      #783                // Field net/minecraft/client/renderer/state/GameRenderState.levelRenderState:Lnet/minecraft/client/renderer/state/level/LevelRenderState;
      53: getfield      #787                // Field net/minecraft/client/renderer/state/level/LevelRenderState.cameraRenderState:Lnet/minecraft/client/renderer/state/level/CameraRenderState;
      56: astore        8
      58: aload         8
      60: getfield      #1179               // Field net/minecraft/client/renderer/state/level/CameraRenderState.viewRotationMatrix:Lorg/joml/Matrix4f;
      63: astore        9
      65: aload         5
      67: ldc_w         #1183               // String matrices
      70: invokeinterface #435,  2          // InterfaceMethod net/minecraft/util/profiling/ProfilerFiller.push:(Ljava/lang/String;)V
      75: new           #579                // class org/joml/Matrix4f
      78: dup
      79: aload         8
      81: getfield      #1185               // Field net/minecraft/client/renderer/state/level/CameraRenderState.projectionMatrix:Lorg/joml/Matrix4f;
      84: invokespecial #1188               // Method org/joml/Matrix4f."<init>":(Lorg/joml/Matrix4fc;)V
      87: astore        10
      89: new           #503                // class com/mojang/blaze3d/vertex/PoseStack
      92: dup
      93: invokespecial #575                // Method com/mojang/blaze3d/vertex/PoseStack."<init>":()V
      96: astore        11
      98: aload_0
      99: aload         8
     101: aload         11
     103: invokevirtual #603                // Method bobHurt:(Lnet/minecraft/client/renderer/state/level/CameraRenderState;Lcom/mojang/blaze3d/vertex/PoseStack;)V
     106: aload         7
     108: getfield      #607                // Field net/minecraft/client/renderer/state/OptionsRenderState.bobView:Z
     111: ifeq          122
     114: aload_0
     115: aload         8
     117: aload         11
     119: invokevirtual #610                // Method bobView:(Lnet/minecraft/client/renderer/state/level/CameraRenderState;Lcom/mojang/blaze3d/vertex/PoseStack;)V
     122: aload         10
     124: aload         11
     126: invokevirtual #1190               // Method com/mojang/blaze3d/vertex/PoseStack.last:()Lcom/mojang/blaze3d/vertex/PoseStack$Pose;
     129: invokevirtual #1194               // Method com/mojang/blaze3d/vertex/PoseStack$Pose.pose:()Lorg/joml/Matrix4f;
     132: invokevirtual #1200               // Method org/joml/Matrix4f.mul:(Lorg/joml/Matrix4fc;)Lorg/joml/Matrix4f;
     135: pop
     136: aload         7
     138: getfield      #1201               // Field net/minecraft/client/renderer/state/OptionsRenderState.screenEffectScale:F
     141: fstore        12
     143: fload_2
     144: aload         4
     146: getfield      #1204               // Field net/minecraft/client/player/LocalPlayer.oPortalEffectIntensity:F
     149: aload         4
     151: getfield      #364                // Field net/minecraft/client/player/LocalPlayer.portalEffectIntensity:F
     154: invokestatic  #1207               // Method net/minecraft/util/Mth.lerp:(FFF)F
     157: fstore        13
     159: aload         4
     161: getstatic     #370                // Field net/minecraft/world/effect/MobEffects.NAUSEA:Lnet/minecraft/core/Holder;
     164: fload_2
     165: invokevirtual #376                // Method net/minecraft/client/player/LocalPlayer.getEffectBlendFactor:(Lnet/minecraft/core/Holder;F)F
     168: fstore        14
     170: fload         13
     172: fload         14
     174: invokestatic  #1211               // Method java/lang/Math.max:(FF)F
     177: fload         12
     179: fload         12
     181: fmul
     182: fmul
     183: fstore        15
     185: fload         15
     187: fconst_0
     188: fcmpl
     189: ifle          291
     192: ldc_w         #563                // float 5.0f
     195: fload         15
     197: fload         15
     199: fmul
     200: ldc_w         #563                // float 5.0f
     203: fadd
     204: fdiv
     205: fload         15
     207: ldc_w         #1214               // float 0.04f
     210: fmul
     211: fsub
     212: fstore        16
     214: fload         16
     216: fload         16
     218: fmul
     219: fstore        16
     221: new           #1215               // class org/joml/Vector3f
     224: dup
     225: fconst_0
     226: getstatic     #1217               // Field net/minecraft/util/Mth.SQRT_OF_TWO:F
     229: fconst_2
     230: fdiv
     231: getstatic     #1217               // Field net/minecraft/util/Mth.SQRT_OF_TWO:F
     234: fconst_2
     235: fdiv
     236: invokespecial #1220               // Method org/joml/Vector3f."<init>":(FFF)V
     239: astore        17
     241: aload_0
     242: getfield      #385                // Field spinningEffectTime:F
     245: fload_2
     246: aload_0
     247: getfield      #382                // Field spinningEffectSpeed:F
     250: fmul
     251: fadd
     252: ldc_w         #1222               // float 0.017453292f
     255: fmul
     256: fstore        18
     258: aload         10
     260: fload         18
     262: aload         17
     264: invokevirtual #1223               // Method org/joml/Matrix4f.rotate:(FLorg/joml/Vector3fc;)Lorg/joml/Matrix4f;
     267: pop
     268: aload         10
     270: fconst_1
     271: fload         16
     273: fdiv
     274: fconst_1
     275: fconst_1
     276: invokevirtual #1227               // Method org/joml/Matrix4f.scale:(FFF)Lorg/joml/Matrix4f;
     279: pop
     280: aload         10
     282: fload         18
     284: fneg
     285: aload         17
     287: invokevirtual #1223               // Method org/joml/Matrix4f.rotate:(FLorg/joml/Vector3fc;)Lorg/joml/Matrix4f;
     290: pop
     291: aload_0
     292: getfield      #109                // Field levelProjectionMatrixBuffer:Lnet/minecraft/client/renderer/ProjectionMatrixBuffer;
     295: aload         10
     297: invokevirtual #1231               // Method net/minecraft/client/renderer/ProjectionMatrixBuffer.getBuffer:(Lorg/joml/Matrix4f;)Lcom/mojang/blaze3d/buffers/GpuBufferSlice;
     300: getstatic     #1234               // Field com/mojang/blaze3d/ProjectionType.PERSPECTIVE:Lcom/mojang/blaze3d/ProjectionType;
     303: invokestatic  #1240               // Method com/mojang/blaze3d/systems/RenderSystem.setProjectionMatrix:(Lcom/mojang/blaze3d/buffers/GpuBufferSlice;Lcom/mojang/blaze3d/ProjectionType;)V
     306: aload         5
     308: ldc_w         #1244               // String fog
     311: invokeinterface #1246,  2         // InterfaceMethod net/minecraft/util/profiling/ProfilerFiller.popPush:(Ljava/lang/String;)V
     316: aload_0
     317: getfield      #70                 // Field fogRenderer:Lnet/minecraft/client/renderer/fog/FogRenderer;
     320: aload         8
     322: getfield      #1249               // Field net/minecraft/client/renderer/state/level/CameraRenderState.fogData:Lnet/minecraft/client/renderer/fog/FogData;
     325: invokevirtual #1253               // Method net/minecraft/client/renderer/fog/FogRenderer.updateBuffer:(Lnet/minecraft/client/renderer/fog/FogData;)V
     328: aload_0
     329: getfield      #70                 // Field fogRenderer:Lnet/minecraft/client/renderer/fog/FogRenderer;
     332: getstatic     #1257               // Field net/minecraft/client/renderer/fog/FogRenderer$FogMode.WORLD:Lnet/minecraft/client/renderer/fog/FogRenderer$FogMode;
     335: invokevirtual #854                // Method net/minecraft/client/renderer/fog/FogRenderer.getBuffer:(Lnet/minecraft/client/renderer/fog/FogRenderer$FogMode;)Lcom/mojang/blaze3d/buffers/GpuBufferSlice;
     338: astore        16
     340: aload         5
     342: ldc           #104                // String level
     344: invokeinterface #1246,  2         // InterfaceMethod net/minecraft/util/profiling/ProfilerFiller.popPush:(Ljava/lang/String;)V
     349: aload_0
     350: getfield      #118                // Field minecraft:Lnet/minecraft/client/Minecraft;
     353: getfield      #408                // Field net/minecraft/client/Minecraft.gui:Lnet/minecraft/client/gui/Gui;
     356: invokevirtual #412                // Method net/minecraft/client/gui/Gui.getBossOverlay:()Lnet/minecraft/client/gui/components/BossHealthOverlay;
     359: invokevirtual #1260               // Method net/minecraft/client/gui/components/BossHealthOverlay.shouldCreateWorldFog:()Z
     362: istore        17
     364: aload_0
     365: getfield      #118                // Field minecraft:Lnet/minecraft/client/Minecraft;
     368: getfield      #440                // Field net/minecraft/client/Minecraft.levelRenderer:Lnet/minecraft/client/renderer/LevelRenderer;
     371: aload_0
     372: getfield      #63                 // Field resourcePool:Lcom/mojang/blaze3d/resource/CrossFrameResourcePool;
     375: aload_1
     376: iload         6
     378: aload         8
     380: aload         9
     382: aload         16
     384: aload         8
     386: getfield      #1249               // Field net/minecraft/client/renderer/state/level/CameraRenderState.fogData:Lnet/minecraft/client/renderer/fog/FogData;
     389: getfield      #1263               // Field net/minecraft/client/renderer/fog/FogData.color:Lorg/joml/Vector4f;
     392: iload         17
     394: ifne          401
     397: iconst_1
     398: goto          402
     401: iconst_0
     402: aload_0
     403: getfield      #10                 // Field gameRenderState:Lnet/minecraft/client/renderer/state/GameRenderState;
     406: getfield      #783                // Field net/minecraft/client/renderer/state/GameRenderState.levelRenderState:Lnet/minecraft/client/renderer/state/level/LevelRenderState;
     409: getfield      #1269               // Field net/minecraft/client/renderer/state/level/LevelRenderState.chunkSectionsToRender:Lnet/minecraft/client/renderer/chunk/ChunkSectionsToRender;
     412: invokevirtual #1273               // Method net/minecraft/client/renderer/LevelRenderer.renderLevel:(Lcom/mojang/blaze3d/resource/GraphicsResourceAllocator;Lnet/minecraft/client/DeltaTracker;ZLnet/minecraft/client/renderer/state/level/CameraRenderState;Lorg/joml/Matrix4fc;Lcom/mojang/blaze3d/buffers/GpuBufferSlice;Lorg/joml/Vector4f;ZLnet/minecraft/client/renderer/chunk/ChunkSectionsToRender;)V
     415: aload         5
     417: ldc_w         #1276               // String hand
     420: invokeinterface #1246,  2         // InterfaceMethod net/minecraft/util/profiling/ProfilerFiller.popPush:(Ljava/lang/String;)V
     425: aload         8
     427: getfield      #461                // Field net/minecraft/client/renderer/state/level/CameraRenderState.entityRenderState:Lnet/minecraft/client/renderer/state/level/CameraEntityRenderState;
     430: getfield      #621                // Field net/minecraft/client/renderer/state/level/CameraEntityRenderState.isSleeping:Z
     433: istore        18
     435: aload_0
     436: getfield      #84                 // Field hudProjection:Lnet/minecraft/client/renderer/Projection;
     439: ldc_w         #425                // float 0.05f
     442: ldc_w         #1278               // float 100.0f
     445: aload         8
     447: getfield      #1279               // Field net/minecraft/client/renderer/state/level/CameraRenderState.hudFov:F
     450: aload_0
     451: getfield      #10                 // Field gameRenderState:Lnet/minecraft/client/renderer/state/GameRenderState;
     454: getfield      #735                // Field net/minecraft/client/renderer/state/GameRenderState.windowRenderState:Lnet/minecraft/client/renderer/state/WindowRenderState;
     457: getfield      #744                // Field net/minecraft/client/renderer/state/WindowRenderState.width:I
     460: i2f
     461: aload_0
     462: getfield      #10                 // Field gameRenderState:Lnet/minecraft/client/renderer/state/GameRenderState;
     465: getfield      #735                // Field net/minecraft/client/renderer/state/GameRenderState.windowRenderState:Lnet/minecraft/client/renderer/state/WindowRenderState;
     468: getfield      #747                // Field net/minecraft/client/renderer/state/WindowRenderState.height:I
     471: i2f
     472: invokevirtual #1282               // Method net/minecraft/client/renderer/Projection.setupPerspective:(FFFFF)V
     475: aload_0
     476: getfield      #115                // Field hud3dProjectionMatrixBuffer:Lnet/minecraft/client/renderer/ProjectionMatrixBuffer;
     479: aload_0
     480: getfield      #84                 // Field hudProjection:Lnet/minecraft/client/renderer/Projection;
     483: invokevirtual #1286               // Method net/minecraft/client/renderer/ProjectionMatrixBuffer.getBuffer:(Lnet/minecraft/client/renderer/Projection;)Lcom/mojang/blaze3d/buffers/GpuBufferSlice;
     486: getstatic     #1234               // Field com/mojang/blaze3d/ProjectionType.PERSPECTIVE:Lcom/mojang/blaze3d/ProjectionType;
     489: invokestatic  #1240               // Method com/mojang/blaze3d/systems/RenderSystem.setProjectionMatrix:(Lcom/mojang/blaze3d/buffers/GpuBufferSlice;Lcom/mojang/blaze3d/ProjectionType;)V
     492: invokestatic  #311                // Method com/mojang/blaze3d/systems/RenderSystem.getDevice:()Lcom/mojang/blaze3d/systems/GpuDevice;
     495: invokevirtual #751                // Method com/mojang/blaze3d/systems/GpuDevice.createCommandEncoder:()Lcom/mojang/blaze3d/systems/CommandEncoder;
     498: aload_0
     499: getfield      #118                // Field minecraft:Lnet/minecraft/client/Minecraft;
     502: invokevirtual #301                // Method net/minecraft/client/Minecraft.getMainRenderTarget:()Lcom/mojang/blaze3d/pipeline/RenderTarget;
     505: invokevirtual #764                // Method com/mojang/blaze3d/pipeline/RenderTarget.getDepthTexture:()Lcom/mojang/blaze3d/textures/GpuTexture;
     508: dconst_1
     509: invokevirtual #826                // Method com/mojang/blaze3d/systems/CommandEncoder.clearDepthTexture:(Lcom/mojang/blaze3d/textures/GpuTexture;D)V
     512: aload_0
     513: aload         8
     515: fload_3
     516: aload         9
     518: invokevirtual #1289               // Method renderItemInHand:(Lnet/minecraft/client/renderer/state/level/CameraRenderState;FLorg/joml/Matrix4fc;)V
     521: aload         5
     523: ldc_w         #1293               // String screenEffects
     526: invokeinterface #1246,  2         // InterfaceMethod net/minecraft/util/profiling/ProfilerFiller.popPush:(Ljava/lang/String;)V
     531: aload_0
     532: getfield      #135                // Field renderBuffers:Lnet/minecraft/client/renderer/RenderBuffers;
     535: invokevirtual #139                // Method net/minecraft/client/renderer/RenderBuffers.bufferSource:()Lnet/minecraft/client/renderer/MultiBufferSource$BufferSource;
     538: astore        19
     540: aload_0
     541: getfield      #230                // Field screenEffectRenderer:Lnet/minecraft/client/renderer/ScreenEffectRenderer;
     544: aload         7
     546: getfield      #612                // Field net/minecraft/client/renderer/state/OptionsRenderState.cameraType:Lnet/minecraft/client/CameraType;
     549: invokevirtual #616                // Method net/minecraft/client/CameraType.isFirstPerson:()Z
     552: iload         18
     554: fload_2
     555: aload_0
     556: getfield      #154                // Field submitNodeStorage:Lnet/minecraft/client/renderer/SubmitNodeStorage;
     559: aload         7
     561: getfield      #624                // Field net/minecraft/client/renderer/state/OptionsRenderState.hideGui:Z
     564: invokevirtual #1295               // Method net/minecraft/client/renderer/ScreenEffectRenderer.renderScreenEffect:(ZZFLnet/minecraft/client/renderer/SubmitNodeCollector;Z)V
     567: aload_0
     568: getfield      #174                // Field featureRenderDispatcher:Lnet/minecraft/client/renderer/feature/FeatureRenderDispatcher;
     571: invokevirtual #567                // Method net/minecraft/client/renderer/feature/FeatureRenderDispatcher.renderAllFeatures:()V
     574: aload         19
     576: invokevirtual #570                // Method net/minecraft/client/renderer/MultiBufferSource$BufferSource.endBatch:()V
     579: aload         5
     581: invokeinterface #448,  1          // InterfaceMethod net/minecraft/util/profiling/ProfilerFiller.pop:()V
     586: aload_0
     587: getfield      #70                 // Field fogRenderer:Lnet/minecraft/client/renderer/fog/FogRenderer;
     590: getstatic     #848                // Field net/minecraft/client/renderer/fog/FogRenderer$FogMode.NONE:Lnet/minecraft/client/renderer/fog/FogRenderer$FogMode;
     593: invokevirtual #854                // Method net/minecraft/client/renderer/fog/FogRenderer.getBuffer:(Lnet/minecraft/client/renderer/fog/FogRenderer$FogMode;)Lcom/mojang/blaze3d/buffers/GpuBufferSlice;
     596: invokestatic  #1299               // Method com/mojang/blaze3d/systems/RenderSystem.setShaderFog:(Lcom/mojang/blaze3d/buffers/GpuBufferSlice;)V
     599: aload_0
     600: getfield      #118                // Field minecraft:Lnet/minecraft/client/Minecraft;
     603: getfield      #1302               // Field net/minecraft/client/Minecraft.debugEntries:Lnet/minecraft/client/gui/components/debug/DebugScreenEntryList;
     606: getstatic     #1306               // Field net/minecraft/client/gui/components/debug/DebugScreenEntries.THREE_DIMENSIONAL_CROSSHAIR:Lnet/minecraft/resources/Identifier;
     609: invokevirtual #1311               // Method net/minecraft/client/gui/components/debug/DebugScreenEntryList.isCurrentlyEnabled:(Lnet/minecraft/resources/Identifier;)Z
     612: ifeq          656
     615: aload         7
     617: getfield      #612                // Field net/minecraft/client/renderer/state/OptionsRenderState.cameraType:Lnet/minecraft/client/CameraType;
     620: invokevirtual #616                // Method net/minecraft/client/CameraType.isFirstPerson:()Z
     623: ifeq          656
     626: aload         7
     628: getfield      #624                // Field net/minecraft/client/renderer/state/OptionsRenderState.hideGui:Z
     631: ifne          656
     634: aload_0
     635: getfield      #118                // Field minecraft:Lnet/minecraft/client/Minecraft;
     638: invokevirtual #1317               // Method net/minecraft/client/Minecraft.getDebugOverlay:()Lnet/minecraft/client/gui/components/DebugScreenOverlay;
     641: aload         8
     643: aload_0
     644: getfield      #10                 // Field gameRenderState:Lnet/minecraft/client/renderer/state/GameRenderState;
     647: getfield      #735                // Field net/minecraft/client/renderer/state/GameRenderState.windowRenderState:Lnet/minecraft/client/renderer/state/WindowRenderState;
     650: getfield      #1321               // Field net/minecraft/client/renderer/state/WindowRenderState.guiScale:I
     653: invokevirtual #1324               // Method net/minecraft/client/gui/components/DebugScreenOverlay.render3dCrosshair:(Lnet/minecraft/client/renderer/state/level/CameraRenderState;I)V
     656: return

  private void extractWindow();
    Code:
       0: aload_0
       1: getfield      #10                 // Field gameRenderState:Lnet/minecraft/client/renderer/state/GameRenderState;
       4: getfield      #735                // Field net/minecraft/client/renderer/state/GameRenderState.windowRenderState:Lnet/minecraft/client/renderer/state/WindowRenderState;
       7: astore_1
       8: aload_0
       9: getfield      #118                // Field minecraft:Lnet/minecraft/client/Minecraft;
      12: invokevirtual #869                // Method net/minecraft/client/Minecraft.getWindow:()Lcom/mojang/blaze3d/platform/Window;
      15: astore_2
      16: aload_1
      17: aload_2
      18: invokevirtual #1330               // Method com/mojang/blaze3d/platform/Window.getWidth:()I
      21: putfield      #744                // Field net/minecraft/client/renderer/state/WindowRenderState.width:I
      24: aload_1
      25: aload_2
      26: invokevirtual #1335               // Method com/mojang/blaze3d/platform/Window.getHeight:()I
      29: putfield      #747                // Field net/minecraft/client/renderer/state/WindowRenderState.height:I
      32: aload_1
      33: aload_2
      34: invokevirtual #1338               // Method com/mojang/blaze3d/platform/Window.getGuiScale:()I
      37: putfield      #1321               // Field net/minecraft/client/renderer/state/WindowRenderState.guiScale:I
      40: aload_1
      41: aload_2
      42: invokevirtual #1341               // Method com/mojang/blaze3d/platform/Window.getAppropriateLineWidth:()F
      45: putfield      #1344               // Field net/minecraft/client/renderer/state/WindowRenderState.appropriateLineWidth:F
      48: aload_1
      49: aload_2
      50: invokevirtual #1347               // Method com/mojang/blaze3d/platform/Window.isMinimized:()Z
      53: putfield      #1350               // Field net/minecraft/client/renderer/state/WindowRenderState.isMinimized:Z
      56: aload_1
      57: aload_2
      58: invokevirtual #1352               // Method com/mojang/blaze3d/platform/Window.isResized:()Z
      61: putfield      #739                // Field net/minecraft/client/renderer/state/WindowRenderState.isResized:Z
      64: return

  private void extractOptions();
    Code:
       0: aload_0
       1: getfield      #10                 // Field gameRenderState:Lnet/minecraft/client/renderer/state/GameRenderState;
       4: getfield      #527                // Field net/minecraft/client/renderer/state/GameRenderState.optionsRenderState:Lnet/minecraft/client/renderer/state/OptionsRenderState;
       7: astore_1
       8: aload_0
       9: getfield      #118                // Field minecraft:Lnet/minecraft/client/Minecraft;
      12: getfield      #1092               // Field net/minecraft/client/Minecraft.options:Lnet/minecraft/client/Options;
      15: astore_2
      16: aload_1
      17: aload_2
      18: invokevirtual #1354               // Method net/minecraft/client/Options.cloudRange:()Lnet/minecraft/client/OptionInstance;
      21: invokevirtual #1358               // Method net/minecraft/client/OptionInstance.get:()Ljava/lang/Object;
      24: checkcast     #1363               // class java/lang/Integer
      27: invokevirtual #1365               // Method java/lang/Integer.intValue:()I
      30: putfield      #1368               // Field net/minecraft/client/renderer/state/OptionsRenderState.cloudRange:I
      33: aload_1
      34: aload_2
      35: invokevirtual #1370               // Method net/minecraft/client/Options.cutoutLeaves:()Lnet/minecraft/client/OptionInstance;
      38: invokevirtual #1358               // Method net/minecraft/client/OptionInstance.get:()Ljava/lang/Object;
      41: checkcast     #1373               // class java/lang/Boolean
      44: invokevirtual #1375               // Method java/lang/Boolean.booleanValue:()Z
      47: putfield      #1378               // Field net/minecraft/client/renderer/state/OptionsRenderState.cutoutLeaves:Z
      50: aload_1
      51: aload_2
      52: invokevirtual #1380               // Method net/minecraft/client/Options.improvedTransparency:()Lnet/minecraft/client/OptionInstance;
      55: invokevirtual #1358               // Method net/minecraft/client/OptionInstance.get:()Ljava/lang/Object;
      58: checkcast     #1373               // class java/lang/Boolean
      61: invokevirtual #1375               // Method java/lang/Boolean.booleanValue:()Z
      64: putfield      #1383               // Field net/minecraft/client/renderer/state/OptionsRenderState.improvedTransparency:Z
      67: aload_1
      68: aload_2
      69: invokevirtual #1385               // Method net/minecraft/client/Options.ambientOcclusion:()Lnet/minecraft/client/OptionInstance;
      72: invokevirtual #1358               // Method net/minecraft/client/OptionInstance.get:()Ljava/lang/Object;
      75: checkcast     #1373               // class java/lang/Boolean
      78: invokevirtual #1375               // Method java/lang/Boolean.booleanValue:()Z
      81: putfield      #1388               // Field net/minecraft/client/renderer/state/OptionsRenderState.ambientOcclusion:Z
      84: aload_1
      85: aload_2
      86: invokevirtual #1390               // Method net/minecraft/client/Options.getMenuBackgroundBlurriness:()I
      89: putfield      #780                // Field net/minecraft/client/renderer/state/OptionsRenderState.menuBackgroundBlurriness:I
      92: aload_1
      93: aload_2
      94: invokevirtual #1393               // Method net/minecraft/client/Options.panoramaSpeed:()Lnet/minecraft/client/OptionInstance;
      97: invokevirtual #1358               // Method net/minecraft/client/OptionInstance.get:()Ljava/lang/Object;
     100: checkcast     #1396               // class java/lang/Double
     103: invokevirtual #1398               // Method java/lang/Double.doubleValue:()D
     106: putfield      #1402               // Field net/minecraft/client/renderer/state/OptionsRenderState.panoramaSpeed:D
     109: aload_1
     110: aload_2
     111: invokevirtual #1404               // Method net/minecraft/client/Options.maxAnisotropyValue:()I
     114: putfield      #1407               // Field net/minecraft/client/renderer/state/OptionsRenderState.maxAnisotropyValue:I
     117: aload_1
     118: aload_2
     119: invokevirtual #1409               // Method net/minecraft/client/Options.textureFiltering:()Lnet/minecraft/client/OptionInstance;
     122: invokevirtual #1358               // Method net/minecraft/client/OptionInstance.get:()Ljava/lang/Object;
     125: checkcast     #802                // class net/minecraft/client/TextureFilteringMethod
     128: putfield      #797                // Field net/minecraft/client/renderer/state/OptionsRenderState.textureFiltering:Lnet/minecraft/client/TextureFilteringMethod;
     131: aload_1
     132: aload_2
     133: invokevirtual #1411               // Method net/minecraft/client/Options.bobView:()Lnet/minecraft/client/OptionInstance;
     136: invokevirtual #1358               // Method net/minecraft/client/OptionInstance.get:()Ljava/lang/Object;
     139: checkcast     #1373               // class java/lang/Boolean
     142: invokevirtual #1375               // Method java/lang/Boolean.booleanValue:()Z
     145: putfield      #607                // Field net/minecraft/client/renderer/state/OptionsRenderState.bobView:Z
     148: aload_1
     149: aload_2
     150: getfield      #1096               // Field net/minecraft/client/Options.hideGui:Z
     153: putfield      #624                // Field net/minecraft/client/renderer/state/OptionsRenderState.hideGui:Z
     156: aload_1
     157: aload_2
     158: invokevirtual #1413               // Method net/minecraft/client/Options.screenEffectScale:()Lnet/minecraft/client/OptionInstance;
     161: invokevirtual #1358               // Method net/minecraft/client/OptionInstance.get:()Ljava/lang/Object;
     164: checkcast     #1396               // class java/lang/Double
     167: invokevirtual #1415               // Method java/lang/Double.floatValue:()F
     170: putfield      #1201               // Field net/minecraft/client/renderer/state/OptionsRenderState.screenEffectScale:F
     173: aload_1
     174: aload_2
     175: invokevirtual #1418               // Method net/minecraft/client/Options.glintSpeed:()Lnet/minecraft/client/OptionInstance;
     178: invokevirtual #1358               // Method net/minecraft/client/OptionInstance.get:()Ljava/lang/Object;
     181: checkcast     #1396               // class java/lang/Double
     184: invokevirtual #1398               // Method java/lang/Double.doubleValue:()D
     187: putfield      #1421               // Field net/minecraft/client/renderer/state/OptionsRenderState.glintSpeed:D
     190: aload_1
     191: aload_2
     192: invokevirtual #1423               // Method net/minecraft/client/Options.glintStrength:()Lnet/minecraft/client/OptionInstance;
     195: invokevirtual #1358               // Method net/minecraft/client/OptionInstance.get:()Ljava/lang/Object;
     198: checkcast     #1396               // class java/lang/Double
     201: invokevirtual #1398               // Method java/lang/Double.doubleValue:()D
     204: putfield      #773                // Field net/minecraft/client/renderer/state/OptionsRenderState.glintStrength:D
     207: aload_1
     208: aload_2
     209: invokevirtual #1425               // Method net/minecraft/client/Options.damageTiltStrength:()Lnet/minecraft/client/OptionInstance;
     212: invokevirtual #1358               // Method net/minecraft/client/OptionInstance.get:()Ljava/lang/Object;
     215: checkcast     #1396               // class java/lang/Double
     218: invokevirtual #1398               // Method java/lang/Double.doubleValue:()D
     221: putfield      #531                // Field net/minecraft/client/renderer/state/OptionsRenderState.damageTiltStrength:D
     224: aload_1
     225: aload_2
     226: invokevirtual #1427               // Method net/minecraft/client/Options.backgroundForChatOnly:()Lnet/minecraft/client/OptionInstance;
     229: invokevirtual #1358               // Method net/minecraft/client/OptionInstance.get:()Ljava/lang/Object;
     232: checkcast     #1373               // class java/lang/Boolean
     235: invokevirtual #1375               // Method java/lang/Boolean.booleanValue:()Z
     238: putfield      #1430               // Field net/minecraft/client/renderer/state/OptionsRenderState.backgroundForChatOnly:Z
     241: aload_1
     242: aload_2
     243: invokevirtual #1432               // Method net/minecraft/client/Options.textBackgroundOpacity:()Lnet/minecraft/client/OptionInstance;
     246: invokevirtual #1358               // Method net/minecraft/client/OptionInstance.get:()Ljava/lang/Object;
     249: checkcast     #1396               // class java/lang/Double
     252: invokevirtual #1415               // Method java/lang/Double.floatValue:()F
     255: putfield      #1435               // Field net/minecraft/client/renderer/state/OptionsRenderState.textBackgroundOpacity:F
     258: aload_1
     259: aload_2
     260: invokevirtual #1437               // Method net/minecraft/client/Options.getCloudStatus:()Lnet/minecraft/client/CloudStatus;
     263: putfield      #1441               // Field net/minecraft/client/renderer/state/OptionsRenderState.cloudStatus:Lnet/minecraft/client/CloudStatus;
     266: aload_1
     267: aload_2
     268: invokevirtual #1445               // Method net/minecraft/client/Options.getCameraType:()Lnet/minecraft/client/CameraType;
     271: putfield      #612                // Field net/minecraft/client/renderer/state/OptionsRenderState.cameraType:Lnet/minecraft/client/CameraType;
     274: aload_1
     275: aload_2
     276: invokevirtual #1449               // Method net/minecraft/client/Options.getEffectiveRenderDistance:()I
     279: putfield      #1452               // Field net/minecraft/client/renderer/state/OptionsRenderState.renderDistance:I
     282: return

  private void extractCamera(net.minecraft.client.DeltaTracker, float, float);
    Code:
       0: aload_0
       1: getfield      #10                 // Field gameRenderState:Lnet/minecraft/client/renderer/state/GameRenderState;
       4: getfield      #783                // Field net/minecraft/client/renderer/state/GameRenderState.levelRenderState:Lnet/minecraft/client/renderer/state/level/LevelRenderState;
       7: getfield      #787                // Field net/minecraft/client/renderer/state/level/LevelRenderState.cameraRenderState:Lnet/minecraft/client/renderer/state/level/CameraRenderState;
      10: astore        4
      12: aload_0
      13: getfield      #77                 // Field mainCamera:Lnet/minecraft/client/Camera;
      16: aload         4
      18: fload_3
      19: invokevirtual #1455               // Method net/minecraft/client/Camera.extractRenderState:(Lnet/minecraft/client/renderer/state/level/CameraRenderState;F)V
      22: aload         4
      24: aload_0
      25: getfield      #77                 // Field mainCamera:Lnet/minecraft/client/Camera;
      28: invokevirtual #1458               // Method net/minecraft/client/Camera.getFluidInCamera:()Lnet/minecraft/world/level/material/FogType;
      31: putfield      #1462               // Field net/minecraft/client/renderer/state/level/CameraRenderState.fogType:Lnet/minecraft/world/level/material/FogType;
      34: aload         4
      36: aload_0
      37: getfield      #70                 // Field fogRenderer:Lnet/minecraft/client/renderer/fog/FogRenderer;
      40: aload_0
      41: getfield      #77                 // Field mainCamera:Lnet/minecraft/client/Camera;
      44: aload_0
      45: getfield      #118                // Field minecraft:Lnet/minecraft/client/Minecraft;
      48: getfield      #1092               // Field net/minecraft/client/Minecraft.options:Lnet/minecraft/client/Options;
      51: invokevirtual #1449               // Method net/minecraft/client/Options.getEffectiveRenderDistance:()I
      54: aload_1
      55: aload_0
      56: fload_2
      57: invokevirtual #1466               // Method getBossOverlayWorldDarkening:(F)F
      60: aload_0
      61: getfield      #118                // Field minecraft:Lnet/minecraft/client/Minecraft;
      64: getfield      #388                // Field net/minecraft/client/Minecraft.level:Lnet/minecraft/client/multiplayer/ClientLevel;
      67: invokevirtual #1469               // Method net/minecraft/client/renderer/fog/FogRenderer.setupFog:(Lnet/minecraft/client/Camera;ILnet/minecraft/client/DeltaTracker;FLnet/minecraft/client/multiplayer/ClientLevel;)Lnet/minecraft/client/renderer/fog/FogData;
      70: putfield      #1249               // Field net/minecraft/client/renderer/state/level/CameraRenderState.fogData:Lnet/minecraft/client/renderer/fog/FogData;
      73: return

  public void resetData();
    Code:
       0: aload_0
       1: getfield      #230                // Field screenEffectRenderer:Lnet/minecraft/client/renderer/ScreenEffectRenderer;
       4: invokevirtual #1473               // Method net/minecraft/client/renderer/ScreenEffectRenderer.resetItemActivation:()V
       7: aload_0
       8: getfield      #118                // Field minecraft:Lnet/minecraft/client/Minecraft;
      11: invokevirtual #1476               // Method net/minecraft/client/Minecraft.getMapTextureManager:()Lnet/minecraft/client/resources/MapTextureManager;
      14: invokevirtual #1480               // Method net/minecraft/client/resources/MapTextureManager.resetData:()V
      17: aload_0
      18: getfield      #77                 // Field mainCamera:Lnet/minecraft/client/Camera;
      21: invokevirtual #1485               // Method net/minecraft/client/Camera.reset:()V
      24: aload_0
      25: iconst_0
      26: putfield      #1034               // Field hasWorldScreenshot:Z
      29: return

  public void displayItemActivation(net.minecraft.world.item.ItemStack);
    Code:
       0: aload_0
       1: getfield      #230                // Field screenEffectRenderer:Lnet/minecraft/client/renderer/ScreenEffectRenderer;
       4: aload_1
       5: aload_0
       6: getfield      #22                 // Field random:Lnet/minecraft/util/RandomSource;
       9: invokevirtual #1486               // Method net/minecraft/client/renderer/ScreenEffectRenderer.displayItemActivation:(Lnet/minecraft/world/item/ItemStack;Lnet/minecraft/util/RandomSource;)V
      12: return

  public net.minecraft.client.Minecraft getMinecraft();
    Code:
       0: aload_0
       1: getfield      #118                // Field minecraft:Lnet/minecraft/client/Minecraft;
       4: areturn

  public float getBossOverlayWorldDarkening(float);
    Code:
       0: fload_1
       1: aload_0
       2: getfield      #405                // Field bossOverlayWorldDarkeningO:F
       5: aload_0
       6: getfield      #402                // Field bossOverlayWorldDarkening:F
       9: invokestatic  #1207               // Method net/minecraft/util/Mth.lerp:(FFF)F
      12: freturn

  public net.minecraft.client.Camera getMainCamera();
    Code:
       0: aload_0
       1: getfield      #77                 // Field mainCamera:Lnet/minecraft/client/Camera;
       4: areturn

  public com.mojang.blaze3d.textures.GpuTextureView lightmap();
    Code:
       0: aload_0
       1: getfield      #844                // Field useUiLightmap:Z
       4: ifeq          17
       7: aload_0
       8: getfield      #40                 // Field uiLightmap:Lnet/minecraft/client/renderer/UiLightmap;
      11: invokevirtual #1490               // Method net/minecraft/client/renderer/UiLightmap.getTextureView:()Lcom/mojang/blaze3d/textures/GpuTextureView;
      14: goto          24
      17: aload_0
      18: getfield      #33                 // Field lightmap:Lnet/minecraft/client/renderer/Lightmap;
      21: invokevirtual #1494               // Method net/minecraft/client/renderer/Lightmap.getTextureView:()Lcom/mojang/blaze3d/textures/GpuTextureView;
      24: areturn

  public com.mojang.blaze3d.textures.GpuTextureView levelLightmap();
    Code:
       0: aload_0
       1: getfield      #33                 // Field lightmap:Lnet/minecraft/client/renderer/Lightmap;
       4: invokevirtual #1494               // Method net/minecraft/client/renderer/Lightmap.getTextureView:()Lcom/mojang/blaze3d/textures/GpuTextureView;
       7: areturn

  public net.minecraft.client.renderer.texture.OverlayTexture overlayTexture();
    Code:
       0: aload_0
       1: getfield      #47                 // Field overlayTexture:Lnet/minecraft/client/renderer/texture/OverlayTexture;
       4: areturn

  public net.minecraft.world.phys.Vec3 projectPointToScreen(net.minecraft.world.phys.Vec3);
    Code:
       0: aload_0
       1: getfield      #77                 // Field mainCamera:Lnet/minecraft/client/Camera;
       4: new           #579                // class org/joml/Matrix4f
       7: dup
       8: invokespecial #581                // Method org/joml/Matrix4f."<init>":()V
      11: invokevirtual #1495               // Method net/minecraft/client/Camera.getViewRotationProjectionMatrix:(Lorg/joml/Matrix4f;)Lorg/joml/Matrix4f;
      14: astore_2
      15: aload_0
      16: getfield      #77                 // Field mainCamera:Lnet/minecraft/client/Camera;
      19: invokevirtual #1498               // Method net/minecraft/client/Camera.position:()Lnet/minecraft/world/phys/Vec3;
      22: astore_3
      23: aload_1
      24: aload_3
      25: invokevirtual #1502               // Method net/minecraft/world/phys/Vec3.subtract:(Lnet/minecraft/world/phys/Vec3;)Lnet/minecraft/world/phys/Vec3;
      28: astore        4
      30: aload_2
      31: aload         4
      33: invokevirtual #1508               // Method net/minecraft/world/phys/Vec3.toVector3f:()Lorg/joml/Vector3f;
      36: invokevirtual #1512               // Method org/joml/Matrix4f.transformProject:(Lorg/joml/Vector3f;)Lorg/joml/Vector3f;
      39: astore        5
      41: new           #1503               // class net/minecraft/world/phys/Vec3
      44: dup
      45: aload         5
      47: invokespecial #1516               // Method net/minecraft/world/phys/Vec3."<init>":(Lorg/joml/Vector3fc;)V
      50: areturn

  public double projectHorizonToScreen();
    Code:
       0: aload_0
       1: getfield      #77                 // Field mainCamera:Lnet/minecraft/client/Camera;
       4: invokevirtual #1519               // Method net/minecraft/client/Camera.xRot:()F
       7: fstore_1
       8: fload_1
       9: ldc_w         #1522               // float -90.0f
      12: fcmpg
      13: ifgt          20
      16: ldc2_w        #1523               // double -Infinityd
      19: dreturn
      20: fload_1
      21: ldc_w         #1525               // float 90.0f
      24: fcmpl
      25: iflt          32
      28: ldc2_w        #1526               // double Infinityd
      31: dreturn
      32: aload_0
      33: getfield      #77                 // Field mainCamera:Lnet/minecraft/client/Camera;
      36: invokevirtual #1528               // Method net/minecraft/client/Camera.getFov:()F
      39: fstore_2
      40: fload_1
      41: ldc_w         #1222               // float 0.017453292f
      44: fmul
      45: f2d
      46: invokestatic  #1531               // Method java/lang/Math.tan:(D)D
      49: fload_2
      50: fconst_2
      51: fdiv
      52: ldc_w         #1222               // float 0.017453292f
      55: fmul
      56: f2d
      57: invokestatic  #1531               // Method java/lang/Math.tan:(D)D
      60: ddiv
      61: dreturn

  public net.minecraft.client.renderer.GlobalSettingsUniform getGlobalSettingsUniform();
    Code:
       0: aload_0
       1: getfield      #98                 // Field globalSettingsUniform:Lnet/minecraft/client/renderer/GlobalSettingsUniform;
       4: areturn

  public com.mojang.blaze3d.platform.Lighting getLighting();
    Code:
       0: aload_0
       1: getfield      #91                 // Field lighting:Lcom/mojang/blaze3d/platform/Lighting;
       4: areturn

  public void setLevel(net.minecraft.client.multiplayer.ClientLevel);
    Code:
       0: aload_1
       1: ifnull        18
       4: aload_0
       5: getfield      #91                 // Field lighting:Lcom/mojang/blaze3d/platform/Lighting;
       8: aload_1
       9: invokevirtual #1535               // Method net/minecraft/client/multiplayer/ClientLevel.dimensionType:()Lnet/minecraft/world/level/dimension/DimensionType;
      12: invokevirtual #1539               // Method net/minecraft/world/level/dimension/DimensionType.cardinalLightType:()Lnet/minecraft/world/level/CardinalLighting$Type;
      15: invokevirtual #1545               // Method com/mojang/blaze3d/platform/Lighting.updateLevel:(Lnet/minecraft/world/level/CardinalLighting$Type;)V
      18: aload_0
      19: getfield      #77                 // Field mainCamera:Lnet/minecraft/client/Camera;
      22: aload_1
      23: invokevirtual #1549               // Method net/minecraft/client/Camera.setLevel:(Lnet/minecraft/client/multiplayer/ClientLevel;)V
      26: return

  public net.minecraft.client.renderer.Panorama getPanorama();
    Code:
       0: aload_0
       1: getfield      #54                 // Field panorama:Lnet/minecraft/client/renderer/Panorama;
       4: areturn

  public void registerPanoramaTextures(net.minecraft.client.renderer.texture.TextureManager);
    Code:
       0: aload_0
       1: getfield      #221                // Field guiRenderer:Lnet/minecraft/client/gui/render/GuiRenderer;
       4: aload_1
       5: invokevirtual #1553               // Method net/minecraft/client/gui/render/GuiRenderer.registerPanoramaTextures:(Lnet/minecraft/client/renderer/texture/TextureManager;)V
       8: return

  private static void lambda$takeAutoScreenshot$0(java.nio.file.Path, com.mojang.blaze3d.platform.NativeImage);
    Code:
       0: invokestatic  #1557               // Method net/minecraft/util/Util.ioPool:()Lnet/minecraft/TracingExecutor;
       3: aload_1
       4: aload_0
       5: invokedynamic #1561,  0           // InvokeDynamic #8:run:(Lcom/mojang/blaze3d/platform/NativeImage;Ljava/nio/file/Path;)Ljava/lang/Runnable;
      10: invokevirtual #1565               // Method net/minecraft/TracingExecutor.execute:(Ljava/lang/Runnable;)V
      13: return

  private static void lambda$takeAutoScreenshot$1(com.mojang.blaze3d.platform.NativeImage, java.nio.file.Path);
    Code:
       0: aload_0
       1: invokevirtual #1571               // Method com/mojang/blaze3d/platform/NativeImage.getWidth:()I
       4: istore_2
       5: aload_0
       6: invokevirtual #1574               // Method com/mojang/blaze3d/platform/NativeImage.getHeight:()I
       9: istore_3
      10: iconst_0
      11: istore        4
      13: iconst_0
      14: istore        5
      16: iload_2
      17: iload_3
      18: if_icmple     33
      21: iload_2
      22: iload_3
      23: isub
      24: iconst_2
      25: idiv
      26: istore        4
      28: iload_3
      29: istore_2
      30: goto          42
      33: iload_3
      34: iload_2
      35: isub
      36: iconst_2
      37: idiv
      38: istore        5
      40: iload_2
      41: istore_3
      42: new           #1572               // class com/mojang/blaze3d/platform/NativeImage
      45: dup
      46: bipush        64
      48: bipush        64
      50: iconst_0
      51: invokespecial #1575               // Method com/mojang/blaze3d/platform/NativeImage."<init>":(IIZ)V
      54: astore        6
      56: aload_0
      57: iload         4
      59: iload         5
      61: iload_2
      62: iload_3
      63: aload         6
      65: invokevirtual #1578               // Method com/mojang/blaze3d/platform/NativeImage.resizeSubRectTo:(IIIILcom/mojang/blaze3d/platform/NativeImage;)V
      68: aload         6
      70: aload_1
      71: invokevirtual #1582               // Method com/mojang/blaze3d/platform/NativeImage.writeToFile:(Ljava/nio/file/Path;)V
      74: aload         6
      76: invokevirtual #1586               // Method com/mojang/blaze3d/platform/NativeImage.close:()V
      79: goto          104
      82: astore        7
      84: aload         6
      86: invokevirtual #1586               // Method com/mojang/blaze3d/platform/NativeImage.close:()V
      89: goto          101
      92: astore        8
      94: aload         7
      96: aload         8
      98: invokevirtual #1001               // Method java/lang/Throwable.addSuppressed:(Ljava/lang/Throwable;)V
     101: aload         7
     103: athrow
     104: aload_0
     105: invokevirtual #1586               // Method com/mojang/blaze3d/platform/NativeImage.close:()V
     108: goto          142
     111: astore        6
     113: getstatic     #1589               // Field LOGGER:Lorg/slf4j/Logger;
     116: ldc_w         #1593               // String Couldn\'t save auto screenshot
     119: aload         6
     121: invokeinterface #1595,  3         // InterfaceMethod org/slf4j/Logger.warn:(Ljava/lang/String;Ljava/lang/Throwable;)V
     126: aload_0
     127: invokevirtual #1586               // Method com/mojang/blaze3d/platform/NativeImage.close:()V
     130: goto          142
     133: astore        9
     135: aload_0
     136: invokevirtual #1586               // Method com/mojang/blaze3d/platform/NativeImage.close:()V
     139: aload         9
     141: athrow
     142: return
    Exception table:
       from    to  target type
          56    74    82   Class java/lang/Throwable
          84    89    92   Class java/lang/Throwable
          42   104   111   Class java/io/IOException
          42   104   133   any
         111   126   133   any
         133   135   133   any

  private void lambda$tryTakeScreenshotIfNeeded$0(java.nio.file.Path);
    Code:
       0: aload_1
       1: iconst_0
       2: anewarray     #1601               // class java/nio/file/LinkOption
       5: invokestatic  #1603               // Method java/nio/file/Files.isRegularFile:(Ljava/nio/file/Path;[Ljava/nio/file/LinkOption;)Z
       8: ifeq          19
      11: aload_0
      12: iconst_1
      13: putfield      #1034               // Field hasWorldScreenshot:Z
      16: goto          24
      19: aload_0
      20: aload_1
      21: invokevirtual #1609               // Method takeAutoScreenshot:(Ljava/nio/file/Path;)V
      24: return

  private void lambda$renderActiveTextDebug$0(net.minecraft.client.renderer.state.gui.GuiRenderState, net.minecraft.client.renderer.state.gui.GuiTextRenderState);
    Code:
       0: aload_2
       1: invokevirtual #1612               // Method net/minecraft/client/renderer/state/gui/GuiTextRenderState.ensurePrepared:()Lnet/minecraft/client/gui/Font$PreparedText;
       4: new           #1618               // class net/minecraft/client/renderer/GameRenderer$1
       7: dup
       8: aload_0
       9: aload_1
      10: aload_2
      11: invokespecial #1620               // Method net/minecraft/client/renderer/GameRenderer$1."<init>":(Lnet/minecraft/client/renderer/GameRenderer;Lnet/minecraft/client/renderer/state/gui/GuiRenderState;Lnet/minecraft/client/renderer/state/gui/GuiTextRenderState;)V
      14: invokeinterface #1623,  2         // InterfaceMethod net/minecraft/client/gui/Font$PreparedText.visit:(Lnet/minecraft/client/gui/Font$GlyphVisitor;)V
      19: return

  private java.lang.String lambda$extractGui$2() throws java.lang.Exception;
    Code:
       0: aload_0
       1: getfield      #118                // Field minecraft:Lnet/minecraft/client/Minecraft;
       4: getfield      #944                // Field net/minecraft/client/Minecraft.screen:Lnet/minecraft/client/gui/screens/Screen;
       7: invokevirtual #1629               // Method java/lang/Object.getClass:()Ljava/lang/Class;
      10: invokevirtual #1633               // Method java/lang/Class.getCanonicalName:()Ljava/lang/String;
      13: areturn

  private java.lang.String lambda$extractGui$1() throws java.lang.Exception;
    Code:
       0: aload_0
       1: getfield      #118                // Field minecraft:Lnet/minecraft/client/Minecraft;
       4: getfield      #944                // Field net/minecraft/client/Minecraft.screen:Lnet/minecraft/client/gui/screens/Screen;
       7: invokevirtual #1629               // Method java/lang/Object.getClass:()Ljava/lang/Class;
      10: invokevirtual #1633               // Method java/lang/Class.getCanonicalName:()Ljava/lang/String;
      13: areturn

  private java.lang.String lambda$extractGui$0() throws java.lang.Exception;
    Code:
       0: aload_0
       1: getfield      #118                // Field minecraft:Lnet/minecraft/client/Minecraft;
       4: invokevirtual #896                // Method net/minecraft/client/Minecraft.getOverlay:()Lnet/minecraft/client/gui/screens/Overlay;
       7: invokevirtual #1629               // Method java/lang/Object.getClass:()Ljava/lang/Class;
      10: invokevirtual #1633               // Method java/lang/Class.getCanonicalName:()Ljava/lang/String;
      13: areturn

  private static java.lang.String lambda$preloadUiShader$0(net.minecraft.server.packs.resources.ResourceProvider, net.minecraft.resources.Identifier, com.mojang.blaze3d.shaders.ShaderType);
    Code:
       0: aload_2
       1: invokevirtual #1639               // Method com/mojang/blaze3d/shaders/ShaderType.idConverter:()Lnet/minecraft/resources/FileToIdConverter;
       4: aload_1
       5: invokevirtual #1645               // Method net/minecraft/resources/FileToIdConverter.idToFile:(Lnet/minecraft/resources/Identifier;)Lnet/minecraft/resources/Identifier;
       8: astore_3
       9: aload_0
      10: aload_3
      11: invokeinterface #1651,  2         // InterfaceMethod net/minecraft/server/packs/resources/ResourceProvider.getResourceOrThrow:(Lnet/minecraft/resources/Identifier;)Lnet/minecraft/server/packs/resources/Resource;
      16: invokevirtual #1657               // Method net/minecraft/server/packs/resources/Resource.openAsReader:()Ljava/io/BufferedReader;
      19: astore        4
      21: aload         4
      23: invokestatic  #1663               // Method org/apache/commons/io/IOUtils.toString:(Ljava/io/Reader;)Ljava/lang/String;
      26: astore        5
      28: aload         4
      30: ifnull        38
      33: aload         4
      35: invokevirtual #1669               // Method java/io/Reader.close:()V
      38: aload         5
      40: areturn
      41: astore        5
      43: aload         4
      45: ifnull        65
      48: aload         4
      50: invokevirtual #1669               // Method java/io/Reader.close:()V
      53: goto          65
      56: astore        6
      58: aload         5
      60: aload         6
      62: invokevirtual #1001               // Method java/lang/Throwable.addSuppressed:(Ljava/lang/Throwable;)V
      65: aload         5
      67: athrow
      68: astore        4
      70: getstatic     #1589               // Field LOGGER:Lorg/slf4j/Logger;
      73: ldc_w         #1672               // String Coudln\'t preload {} shader {}: {}
      76: iconst_3
      77: anewarray     #2                  // class java/lang/Object
      80: dup
      81: iconst_0
      82: aload_2
      83: aastore
      84: dup
      85: iconst_1
      86: aload_1
      87: aastore
      88: dup
      89: iconst_2
      90: aload         4
      92: aastore
      93: invokeinterface #1674,  3         // InterfaceMethod org/slf4j/Logger.error:(Ljava/lang/String;[Ljava/lang/Object;)V
      98: aconst_null
      99: areturn
    Exception table:
       from    to  target type
          21    28    41   Class java/lang/Throwable
          48    53    56   Class java/lang/Throwable
           9    38    68   Class java/io/IOException
          41    68    68   Class java/io/IOException

  static {};
    Code:
       0: ldc_w         #1678               // String blur
       3: invokestatic  #261                // Method net/minecraft/resources/Identifier.withDefaultNamespace:(Ljava/lang/String;)Lnet/minecraft/resources/Identifier;
       6: putstatic     #286                // Field BLUR_POST_CHAIN_ID:Lnet/minecraft/resources/Identifier;
       9: invokestatic  #1680               // Method com/mojang/logging/LogUtils.getLogger:()Lorg/slf4j/Logger;
      12: putstatic     #1589               // Field LOGGER:Lorg/slf4j/Logger;
      15: return
}
